casr/casr_90150h.vhd
--------------------------------------------------------------------------------
-- Title       : Cellular Automata Shift Register (CASR) (Rule 90/150 Hybrid) 
-- Project     : hdl_rand
--------------------------------------------------------------------------------
-- File        : casr_90150h.vhd
-- Author      : Ameer Shalabi <ameershalabi94@gmail.com>
-- Created     : Sun Jan 11 10:20:17 2026
-- Last update : Sun Jan 11 12:23:39 2026
-- Platform    : -
-- Standard    : VHDL-2008
--------------------------------------------------------------------------------
-- Description: A Cellular Automata Shift Register (CASR) applying rules 90
-- and rule 150 selectively. Has three output modes: 
-- 1) State LSB output (serial LSB)
-- 2) State MSB output (serial MSB)
-- 3) Full state output (parallel)
--------------------------------------------------------------------------------
library ieee;
use ieee.std_logic_1164.all;
use ieee.numeric_std.all;

entity casr_90150h is
  generic (
    w_casr_g : integer := 8;
    -- control which bit to output
    -- '0' : output LSB bit
    -- '1' : output MSB bit
    o_bit_g : std_logic := '0';
    -- mode
    -- '0' : output is serial mode
    -- '1' : output is parallel
    o_mode_g : std_logic := '0';
    -- rule vector mode
    -- '0' : rule vector is static
    -- stored when seed is loaded
    -- '1' : rule vector is dynamic
    -- stored when rule_i chnages
    r_dyn_g : std_logic := '0'
  );
  port (
    -- ctrl ports
    clk : in std_logic; -- clock pin
    rst : in std_logic; -- active low rest pin
    clr : in std_logic; -- clear pin
    enb : in std_logic; -- enable pin

    seed_i : in std_logic_vector(w_casr_g-1 downto 0);
    rule_i : in std_logic_vector(w_casr_g-1 downto 0);
    init_i : in std_logic;
    gen_i  : in std_logic;

    valid_o : out std_logic;
    state_o : out std_logic_vector(w_casr_g-1 downto 0)

  );

end entity casr_90150h;

architecture arch of casr_90150h is

  signal clr_r  : std_logic;
  signal enb_r  : std_logic;
  signal gen_r  : std_logic;

  -- extended casr for generating the next state
  -- two additional bits are used to connect the 
  -- register ends
  signal ext_casr_r : std_logic_vector(w_casr_g+1 downto 0);

  -- register to store the bit rules
  signal rule_r : std_logic_vector(w_casr_g-1 downto 0);

  -- output bit signals
  signal gen_valid   : std_logic;
  signal gen_valid_r : std_logic;
  signal o_bit       : std_logic;

begin

  -- Generate output bit and oputput modes
  -- When o_mode_g = '0' 
  -- Output is serial:
  -- i.e. a single bit is outputed at the LSB of the 
  -- state_o port. All other state_o bits are '0'
  -- -- if o_bit_g = '0', serial LSB mode :
  -- -- -- output bit is LSB of CASR state
  -- -- if o_bit_g = '1', serial MSB mode :
  -- -- -- output bit is MSB of CASR state

  -- connect output bit to LSB of next state
  gen_out_lsb_0 : if (o_bit_g = '0') generate
    o_bit <= ext_casr_r(w_casr_g+1);
  end generate gen_out_lsb_0;

  -- connect output bit to MSB of next state
  gen_out_lsb_1 : if (o_bit_g = '1') generate
    o_bit <= ext_casr_r(0);
  end generate gen_out_lsb_1;

  -- gen serial mode
  gen_serial_mode : if (o_mode_g = '0') generate

    serial_output_proc : process (o_bit)
    begin
      state_o    <= (others => '0');
      state_o(0) <= o_bit;
    end process serial_output_proc;

  end generate gen_serial_mode;

  -- When o_mode_g = '1'
  -- Full state output (parallel mode)
  -- i.e. all of the CASR state is put to the state_o
  -- in this mode, o_bit_g is not effective

  gen_parallel_mode : if (o_mode_g = '1') generate
    state_o <= ext_casr_r(w_casr_g downto 1);
  end generate gen_parallel_mode;

  -- when r_dyn_g = '0'
  -- store rule_i into register only when init_i is
  -- high. Only a single rule vector can be used for 
  -- each seed
  gen_static_rule_vector : if (r_dyn_g = '0') generate

    gen_static_rule_proc : process (clk, rst)
    begin
      if (rst = '0') then
        rule_r <= (others => '0');
      elsif rising_edge(clk) then
        if (enb_r = '1') then
          -- store the rule vector only when init is done
          if (init_i = '1') then
            rule_r <= rule_i;
          end if;

          if (clr_r = '1') then
            rule_r <= (others => '0');
          end if;

        end if;
      end if;
    end process gen_static_rule_proc;

  end generate gen_static_rule_vector;

  -- when r_dyn_g = '1'
  -- store rule_i into register at every clock cycle 
  -- when the block is enabled. multiple rule vectors
  -- can be used with a single seed
  gen_dynamic_rule_vector : if (r_dyn_g = '0') generate

    gen_dynamic_rule_proc : process (clk, rst)
    begin
      if (rst = '0') then
        rule_r <= (others => '0');
      elsif rising_edge(clk) then
        if (enb_r = '1') then
          -- store the rule vector at every enabled clock cycle
          rule_r <= rule_i;
          if (clr_r = '1') then
            rule_r <= (others => '0');
          end if;

        end if;
      end if;
    end process gen_dynamic_rule_proc;

  end generate gen_dynamic_rule_vector;


  ctrl_proc : process (clk, rst)
  begin
    if (rst = '0') then
      clr_r <= '0';
      enb_r <= '0';
    elsif rising_edge(clk) then
      clr_r <= clr;
      enb_r <= enb;
    end if;
  end process ctrl_proc;

  -- the extended casr is divided into two bit groups
  -- state bits (s), extention bits (e) as follows
  -- MSBext    
  -- |<-------|
  -- ||-state-|
  -- esss...ssse
  --  |------->|
  --           LSBext

  -- output bit is valid when
  gen_valid <= '1' when gen_valid_r = '1' and gen_r = '1' else '0';

  gen_proc : process (clk, rst)
    variable l              : std_logic;
    variable c              : std_logic;
    variable r              : std_logic;
    variable exp1           : std_logic;
    variable new_ext_casr_v : std_logic_vector(w_casr_g+1 downto 0);

  begin
    if (rst = '0') then
      gen_r       <= '0';
      gen_valid_r <= '0';
      ext_casr_r  <= (others => '0');
    elsif rising_edge(clk) then
      if (enb_r = '1') then
        gen_r  <= gen_i;
        -- output is invalid by default
        gen_valid_r <= '0';

        -- load the seed when init_i is high
        if (init_i = '1') then
          ext_casr_r(w_casr_g downto 1) <= seed_i;
          -- connect LSBext to the MSB of state
          ext_casr_r(0) <= seed_i(w_casr_g-1);
          -- connect MSBext to the LSB of state
          ext_casr_r(w_casr_g+1) <= seed_i(0);
          -- first output after init is invalid as
          -- it is the o_bit of the seed
          gen_valid_r <= '0';

        else
          -- if gen_i is high and init_i is low,
          -- generate the next state by applying the 
          -- expression on the left bit, state bit, and
          -- right bit
          if (gen_r = '1') then
            -- if generate is high, the first output is not yet
            -- valid, so valid is delayed a single clock cycle
            gen_valid_r <= '1';
            generate_next_state : for b in 1 to w_casr_g loop
              -- get left bit of state bit b
              l := ext_casr_r(b-1);
              -- get state bit b
              c := ext_casr_r(b);
              -- get right bit of state bit b
              r := ext_casr_r(b+1);

              -- for each bit, check associated rule.
              -- when rule_r(b-1) = '0', use rule 90
              -- when rule_r(b-1) = '1', use rule 150
              if (rule_r(b-1) = '0') then
                -- generate next bit state using rule 90
                exp1 := l xor r;
              else
                -- generate next bit state using rule 150
                exp1 := l xor c xor r;
              end if;

              -- store the new state bit
              new_ext_casr_v(b) := exp1;
              -- generate the extention bits for next round
              new_ext_casr_v(0)          := new_ext_casr_v(w_casr_g);
              new_ext_casr_v(w_casr_g+1) := new_ext_casr_v(1);
            end loop generate_next_state;
            ext_casr_r <= new_ext_casr_v;
          end if;
        end if;
        if (clr_r = '1') then
          gen_r       <= '0';
          gen_valid_r <= '0';
        end if;
      end if;
    end if;
  end process gen_proc;

  valid_o <= gen_valid;

end architecture arch;

casr/verif/casr90150h/sim.vcd
$date
  Wed Feb  4 22:37:06 2026
$end
$version
  GHDL v0
$end
$timescale
  1 ps
$end
$scope module standard $end
$upscope $end
$scope module std_logic_1164 $end
$upscope $end
$scope module numeric_std $end
$upscope $end
$scope module casr_90150h $end
$var reg 1 ! clk $end
$var reg 1 " rst $end
$var reg 1 # clr $end
$var reg 1 $ enb $end
$var reg 512 % seed_i[511:0] $end
$var reg 512 & rule_i[511:0] $end
$var reg 1 ' init_i $end
$var reg 1 ( gen_i $end
$var reg 1 ) valid_o $end
$var reg 512 * state_o[511:0] $end
$var reg 1 + clr_r $end
$var reg 1 , enb_r $end
$var reg 1 - gen_r $end
$var reg 514 . ext_casr_r[513:0] $end
$var reg 512 / rule_r[511:0] $end
$var reg 1 0 gen_valid $end
$var reg 1 1 gen_valid_r $end
$var reg 1 2 o_bit $end
$scope module gen_out_lsb_0 $end
$upscope $end
$scope module gen_parallel_mode $end
$upscope $end
$scope module gen_static_rule_vector $end
$upscope $end
$scope module gen_dynamic_rule_vector $end
$upscope $end
$upscope $end
$enddefinitions $end
#0
1!
0"
0#
0$
b00000000000000000000000000000000000000000000000000000000000000000000000000000000000000000000000000000000000000000000000000000000000000000000000000000000000000000000000000000000000000000000000000000000000000000000000000000000000000000000000000000000000000000000000000000000000000000000000000000000000000000000000000000000000000000000000000000000000000000000000000000000000000000000000000000000000000000000000000000000000000000000000000000000000000000000000000000000000000000000000000000000000000000000000000000000 %
b00000000000000000000000000000000000000000000000000000000000000000000000000000000000000000000000000000000000000000000000000000000000000000000000000000000000000000000000000000000000000000000000000000000000000000000000000000000000000000000000000000000000000000000000000000000000000000000000000000000000000000000000000000000000000000000000000000000000000000000000000000000000000000000000000000000000000000000000000000000000000000000000000000000000000000000000000000000000000000000000000000000000000000000000000000000 &
0'
0(
0)
b00000000000000000000000000000000000000000000000000000000000000000000000000000000000000000000000000000000000000000000000000000000000000000000000000000000000000000000000000000000000000000000000000000000000000000000000000000000000000000000000000000000000000000000000000000000000000000000000000000000000000000000000000000000000000000000000000000000000000000000000000000000000000000000000000000000000000000000000000000000000000000000000000000000000000000000000000000000000000000000000000000000000000000000000000000000 *
0+
0,
0-
b0000000000000000000000000000000000000000000000000000000000000000000000000000000000000000000000000000000000000000000000000000000000000000000000000000000000000000000000000000000000000000000000000000000000000000000000000000000000000000000000000000000000000000000000000000000000000000000000000000000000000000000000000000000000000000000000000000000000000000000000000000000000000000000000000000000000000000000000000000000000000000000000000000000000000000000000000000000000000000000000000000000000000000000000000000000000 .
b00000000000000000000000000000000000000000000000000000000000000000000000000000000000000000000000000000000000000000000000000000000000000000000000000000000000000000000000000000000000000000000000000000000000000000000000000000000000000000000000000000000000000000000000000000000000000000000000000000000000000000000000000000000000000000000000000000000000000000000000000000000000000000000000000000000000000000000000000000000000000000000000000000000000000000000000000000000000000000000000000000000000000000000000000000000 /
00
01
02
#5000
0!
#10000
1!
1"
1#
1$
#15000
0!
#20000
1!
0#
b00101000010111110100010010101011001100100001111011010101111001011101011111110000010010111011010110101101010011010101101110011000000111101100011011110100111000001000110101000111010111010101111110001110011111011011101110111001010101011111011000111000100111011111110001111111111111011101010111100111010011101111010011000010010011110111111100010111001000101110111101110101100010101100010011011011001100111111101001011110001111000100110110001010001011000011011010111101000011110111010110100100101010111110000001111101 %
b11111100011111111111110111010101111001110100111011110100110000100100111101111111000101110010001011101111011101011000101011000100110110110011001111111010010111100011110001001101100010100010110000110110101111010000111101110101101001001010101111100000011111010010100001011111010001001010101100110010000111101101010111100101110101111111000001001011101101011010110101001101010110111001100000011110110001101111010011100000100011010100011101011101010111111000111001111101101110111011100101010101111101100011100010011101 &
1'
1(
1+
1,
#25000
0!
#30000
1!
0'
b00101000010111110100010010101011001100100001111011010101111001011101011111110000010010111011010110101101010011010101101110011000000111101100011011110100111000001000110101000111010111010101111110001110011111011011101110111001010101011111011000111000100111011111110001111111111111011101010111100111010011101111010011000010010011110111111100010111001000101110111101110101100010101100010011011011001100111111101001011110001111000100110110001010001011000011011010111101000011110111010110100100101010111110000001111101 *
0+
b1001010000101111101000100101010110011001000011110110101011110010111010111111100000100101110110101101011010100110101011011100110000001111011000110111101001110000010001101010001110101110101011111100011100111110110111011101110010101010111110110001110001001110111111100011111111111110111010101111001110100111011110100110000100100111101111111000101110010001011101111011101011000101011000100110110110011001111111010010111100011110001001101100010100010110000110110101111010000111101110101101001001010101111100000011111010 .
12
#35000
0!
#40000
1!
1-
bXXXXXX000XXXXXXXXXXXXX0XXX0X0X0XXXX00XXX0X00XXX0XXXX0X00XX0000X00X00XXXX0XXXXXXX000X0XXX00X000X0XXX0XXXX0XXX0X0XX000X0X0XX000X00XX0XX0XX00XX00XXXXXXX0X00X0XXXX000XXXX000X00XX0XX000X0X000X0XX0000XX0XX0X0XXXX0X0000XXXX0XXX0X0XX0X00X00X0X0X0XXXXX000000XXXXX0X00X0X0000X0XXXXX0X000X00X0X0X0XX00XX00X0000XXXX0XX0X0X0XXXX00X0XXX0X0XXXXXXX00000X00X0XXX0XX0X0XX0X0XX0X0X00XX0X0X0XX0XXX00XX000000XXXX0XX000XX0XXXX0X00XXX00000X000XX0X0X000XXX0X0XXX0X0X0XXXXXX000XXX00XXXXX0XX0XXX0XXX0XXX00X0X0X0X0XXXXX0XX000XXX000X00XXX0X /
#45000
0!
#50000
1!
1)
b11101100110011100110111110000010110111110011110000010101111110010000001101101000101100011001000100100001011110010001000001111100001010001110110001100011111100010101000001101000000111000001110011011101111110001010000110011111000001011011010101001101011010000010111010011111010000011100000000011111001101000100011100100101111111100011000110100110111101000000010000010100110110100110101111000001111111001111100111010011011010101111100011011001010000100111000000011001100100100110000010011111101000000001000011011001 *
b1111011001100111001101111100000101101111100111100000101011111100100000011011010001011000110010001001000010111100100010000011111000010100011101100011000111111000101010000011010000001110000011100110111011111100010100001100111110000010110110101010011010110100000101110100111110100000111000000000111110011010001000111001001011111111000110001101001101111010000000100000101001101101001101011110000011111110011111001110100110110101011111000110110010100001001110000000110011001001001100000100111111010000000010000110110011 .
10
11
#55000
0!
#60000
1!
b11000011101101011000010101000100000101101110101000110101110011101000010000001101001010101110101011110011001111111010100010000010010011011000111010010100010010100001100010101100001111100011101111000001101101010001001011100100100011010001000101111100000011000110001001101110011000111110000000100011111001101110100011111100110101010100101110011100001001100000111000100111100000111110101001100011110000110111111110001111011010001100110110000111011001111101100000100110011111111101000101100101001100000011100101000110 *
b0110000111011010110000101010001000001011011101010001101011100111010000100000011010010101011101010111100110011111110101000100000100100110110001110100101000100101000011000101011000011111000111011110000011011010100010010111001001000110100010001011111000000110001100010011011100110001111100000001000111110011011101000111111001101010101001011100111000010011000001110001001111000001111101010011000111100001101111111100011110110100011001101100001110110011111011000001001100111111111010001011001010011000000111001010001101 .
02
#65000
0!
#70000
1!
b00100110100001000100110101101110001000001110101101000101101110000100111000010001110000101000001001111100110101010000110111000101111101001101100011110010111110110010010100000010011010010100001001100011000001011010111011011111110110001010101100100110000100101101010110100101101101101001000001110100001110000110010101100011000101010111001011111110011110110001011101011001110001011010100111110100101001010011010001011001011011011011100011001000001110111101010001111011111110111101101100111101110010000101011000101010 *
b0001001101000010001001101011011100010000011101011010001011011100001001110000100011100001010000010011111001101010100001101110001011111010011011000111100101111101100100101000000100110100101000010011000110000010110101110110111111101100010101011001001100001001011010101101001011011011010010000011101000011100001100101011000110001010101110010111111100111101100010111010110011100010110101001111101001010010100110100010110010110110110111000110010000011101111010100011110111111101111011011001111011100100001010110001010100 .
#75000
0!
#80000
1!
b01111010010011101111000100101111011100011110100101101101001011001111010100111010011001100100011110101011100101011001010110101101110000111100110101101110110100011111110010000101111011100010010111010101100011001000010010000101110111011010100011111111001111001100000110011100101100101110100011100010011101001011110100010110101101010010110011001001111110101010000001010110001010000000111100000111100111001100011011011110011000001010110110111100011100011100011010110011101100011100001011110000101101001001011101001001 *
b1011110100100111011110001001011110111000111101001011011010010110011110101001110100110011001000111101010111001010110010101101011011100001111001101011011101101000111111100100001011110111000100101110101011000110010000100100001011101110110101000111111110011110011000001100111001011001011101000111000100111010010111101000101101011010100101100110010011111101010100000010101100010100000001111000001111001110011000110110111100110000010101101101111000111000111000110101100111011000111000010111100001011010010010111010010010 .
12
#85000
0!
#90000
1!
b00110001111101000110101111001100001110100110111000001000110011111101010111010011111110011010111000101001111101000110000100001001101001010111110100000000100110110011101101001100101000010111110101010101010100110100111101001100110100010010110101100001110110111110001111101011001111000000110110010111110001111011000110100010101001011110111110111110101110001011000011000011010011000001000110001010011100110010101000010011111100010000100010111010100010101110100000001111000010101110010011001001100001110111010100111111 *
b1001100011111010001101011110011000011101001101110000010001100111111010101110100111111100110101110001010011111010001100001000010011010010101111101000000001001101100111011010011001010000101111101010101010101001101001111010011001101000100101101011000011101101111100011111010110011110000001101100101111100011110110001101000101010010111101111101111101011100010110000110000110100110000010001100010100111001100101010000100111111000100001000101110101000101011101000000011110000101011100100110010011000011101110101001111110 .
#95000
0!
#100000
1!
b11001011011001101000101110111010010010111010010100010101001110100000010000011101000111101010100101101110011001101111001010010111000110010111010110000001011000011101001101110011100100100110100000010100000111100011011001111011010010101110010100010011000000110001011001101000111000100001010011110110011010100010101000110100100111001100100010101000100111011001100110100110011101100011101111011011100111011110000100101110100110111001010100110000010110100010110000010100100110100001101110110110010010110110000011111100 *
b0110010110110011010001011101110100100101110100101000101010011101000000100000111010001111010101001011011100110011011110010100101110001100101110101100000010110000111010011011100111001001001101000000101000001111000110110011110110100101011100101000100110000001100010110011010001110001000010100111101100110101000101010001101001001110011001000101010001001110110011001101001100111011000111011110110111001110111100001001011101001101110010101001100000101101000101100000101001001101000011011101101100100101101100000111111001 .
02
#105000
0!
#110000
1!
b00111011000110001101101100111001111100011001110010110100111010110000111000101001101001000010011000000101100110100001111011100001101001110110000001000010001100110101111100011111011011111100110000110110001011110111000110111010001100000001100110101111100001101010011110101101111101010010001110100101111010110100000101010111111000110011010100001101111000000111011010011011100001010111001001000000011100011101001011101010111100111110010111101000110000110100001000110111111000110010001110100011111100010101000100011011 *
b1001110110001100011011011001110011111000110011100101101001110101100001110001010011010010000100110000001011001101000011110111000011010011101100000010000100011001101011111000111110110111111001100001101100010111101110001101110100011000000011001101011111000011010100111101011011111010100100011101001011110101101000001010101111110001100110101000011011110000001110110100110111000010101110010010000000111000111010010111010101111001111100101111010001100001101000010001101111110001100100011101000111111000101010001000110110 .
12
#115000
0!
#120000
1!
b11010011101001010000001011111110111110101111101110000111011000011001010101101110100111100111110100001100111010010011100001110011000111100101000011100111011011010000110110111100011000100111001001000001011001000101101010011001010110000011011000101000110010100011110010000000010101001111010110111001001010010110001101000001111101001100000010010100100100001111001001110011110010010100110110100000100110111001110001000000000111110111110001101101101001000010011101000001100101001111011110010111111010100001101010100010 *
b0110100111010010100000010111111101111101011111011100001110110000110010101011011101001111001111101000011001110100100111000011100110001111001010000111001110110110100001101101111000110001001110010010000010110010001011010100110010101100000110110001010001100101000111100100000000101010011110101101110010010100101100011010000011111010011000000100101001001000011110010011100111100100101001101101000001001101110011100010000000001111101111100011011011010010000100111010000011001010011110111100101111110101000011010101000101 .
02
#125000
0!
#130000
1!
0(
b00011110101111011000010001010110011010101100000001001001001100111110010100000100011001011110010010010011110001111110010010011111101010011001100101011111001000001001000110101010111101111111110110100010010111101001001001101111000111000101010101100101101110010100111101000000110001110011000010011110110011100011011001100010110001110010000101100011111110010011110110011111001111110011010110010001111110000110001011100000001111000000001010100000100111100101101101100010011100110010010111110001110000110010000010010100 *
b0000111101011110110000100010101100110101011000000010010010011001111100101000001000110010111100100100100111100011111100100100111111010100110011001010111110010000010010001101010101111011111111101101000100101111010010010011011110001110001010101011001011011100101001111010000001100011100110000100111101100111000110110011000101100011100100001011000111111100100111101100111110011111100110101100100011111100001100010111000000011110000000010101000001001111001011011011000100111001100100101111100011100001100100000100101000 .
