casr/casr_30.vhd
--------------------------------------------------------------------------------
-- Title       : Cellular Automata Shift Register (CASR) (Rule 30) 
-- Project     : hdl_rand
--------------------------------------------------------------------------------
-- File        : casr_30.vhd
-- Author      : Ameer Shalabi <ameershalabi94@gmail.com>
-- Created     : Fri Jan  9 14:22:18 2026
-- Last update : Tue Feb 10 15:15:17 2026
-- Platform    : -
-- Standard    : VHDL-2008
--------------------------------------------------------------------------------
-- Description: A Cellular Automata Shift Register (CASR) applying basic
-- rule 30. Has three output modes: 
-- 1) State LSB output (serial LSB)
-- 2) State MSB output (serial MSB)
-- 3) Full state output (parallel)
--------------------------------------------------------------------------------
library ieee;
use ieee.std_logic_1164.all;
use ieee.numeric_std.all;

entity casr_30 is
  generic (
    w_casr_g : integer := 8;
    -- control which bit to output
    -- '0' : output LSB bit
    -- '1' : output MSB bit
    o_bit_g : std_logic := '0';
    -- mode
    -- '0' : output is serial mode
    -- '1' : output is parallel
    o_mode_g : std_logic := '0'
  );
  port (
    -- ctrl ports
    clk : in std_logic; -- clock pin
    rst : in std_logic; -- active low rest pin
    clr : in std_logic; -- clear pin
    enb : in std_logic; -- enable pin

    seed_i : in std_logic_vector(w_casr_g-1 downto 0);
    init_i : in std_logic;
    gen_i  : in std_logic;

    valid_o : out std_logic;
    state_o : out std_logic_vector(w_casr_g-1 downto 0)

  );

end entity casr_30;

architecture arch of casr_30 is

  signal clr_r : std_logic;
  signal enb_r : std_logic;
  signal gen_r : std_logic;

  -- extended casr for generating the next state
  -- two additional bits are used to connect the 
  -- register ends
  signal ext_casr_r   : std_logic_vector(w_casr_g+1 downto 0);
  signal seed_valid_r : std_logic;

  -- output bit signals
  signal gen_valid   : std_logic;
  signal gen_valid_r : std_logic;
  signal o_bit       : std_logic;

begin

  -- Generate output bit and oputput modes
  -- When o_mode_g = '0' 
  -- Output is serial:
  -- i.e. a single bit is outputed at the LSB of the 
  -- state_o port. All other state_o bits are '0'
  -- -- if o_bit_g = '0', serial LSB mode :
  -- -- -- output bit is LSB of CASR state
  -- -- if o_bit_g = '1', serial MSB mode :
  -- -- -- output bit is MSB of CASR state

  -- connect output bit to LSB of next state
  gen_out_lsb_0 : if (o_bit_g = '0') generate
    o_bit <= ext_casr_r(w_casr_g+1);
  end generate gen_out_lsb_0;

  -- connect output bit to MSB of next state
  gen_out_lsb_1 : if (o_bit_g = '1') generate
    o_bit <= ext_casr_r(0);
  end generate gen_out_lsb_1;

  -- gen serial mode
  gen_serial_mode : if (o_mode_g = '0') generate

    serial_output_proc : process (o_bit)
    begin
      state_o    <= (others => '0');
      state_o(0) <= o_bit;
    end process serial_output_proc;

  end generate gen_serial_mode;

  -- When o_mode_g = '1'
  -- Full state output (parallel mode)
  -- i.e. all of the CASR state is put to the state_o
  -- in this mode, o_bit_g is not effective

  gen_parallel_mode : if (o_mode_g = '1') generate
    state_o <= ext_casr_r(w_casr_g downto 1);
  end generate gen_parallel_mode;


  ctrl_proc : process (clk, rst)
  begin
    if (rst = '0') then
      clr_r <= '0';
      enb_r <= '0';
    elsif rising_edge(clk) then
      clr_r <= clr;
      enb_r <= enb;
    end if;
  end process ctrl_proc;

  -- the extended casr is divided into two bit groups
  -- state bits (s), extention bits (e) as follows
  -- MSBext    
  -- |<-------|
  -- ||-state-|
  -- esss...ssse
  --  |------->|
  --           LSBext

  -- output bit is valid when
  gen_valid <= '1' when gen_valid_r = '1' else '0'; --and gen_r = '1' else '0';

  gen_proc : process (clk, rst)
    variable l              : std_logic;
    variable c              : std_logic;
    variable r              : std_logic;
    variable exp1           : std_logic;
    variable exp2           : std_logic;
    variable exp3           : std_logic;
    variable new_ext_casr_v : std_logic_vector(w_casr_g+1 downto 0);

  begin
    if (rst = '0') then
      gen_r        <= '0';
      gen_valid_r  <= '0';
      seed_valid_r <= '0';
      ext_casr_r   <= (others => '0');
    elsif rising_edge(clk) then
      if (enb_r = '1') then
        gen_r <= gen_i;
        -- output is invalid by default
        gen_valid_r <= '0';

        -- load the seed when init_i is high
        if (init_i = '1') then
          ext_casr_r(w_casr_g downto 1) <= seed_i;
          -- connect LSBext to the MSB of state
          ext_casr_r(0) <= seed_i(w_casr_g-1);
          -- connect MSBext to the LSB of state
          ext_casr_r(w_casr_g+1) <= seed_i(0);
          -- first output after init is invalid as
          -- it is the o_bit of the seed
          gen_valid_r  <= '0';
          seed_valid_r <= '1';

        -- if gen_i is high and init_i is low,
        -- generate the next state by applying the 
        -- expression on the left bit, state bit, and
        -- right bit
        elsif (gen_r = '1' and seed_valid_r = '1') then
          -- if generate is high, the first output is not yet
          -- valid, so valid is delayed a single clock cycle
          gen_valid_r <= '1';
          generate_next_state : for b in 1 to w_casr_g loop
            -- get left bit of state bit b
            l := ext_casr_r(b-1);
            -- get state bit b
            c := ext_casr_r(b);
            -- get right bit of state bit b
            r := ext_casr_r(b+1);
            -- apply expression l & not c & not r
            exp1 := l and not c and not r;
            -- apply expression not l & c
            exp2 := not l and c;
            -- apply expression not l & not c & r
            exp3 := not l and not c and r;

            -- store the new state bit
            new_ext_casr_v(b) := exp1 or exp2 or exp3;
            -- generate the extention bits for next round
            new_ext_casr_v(0)          := new_ext_casr_v(w_casr_g);
            new_ext_casr_v(w_casr_g+1) := new_ext_casr_v(1);
          end loop generate_next_state;
          ext_casr_r <= new_ext_casr_v;
        end if;
        if (clr_r = '1') then
          gen_r        <= '0';
          gen_valid_r  <= '0';
          seed_valid_r <= '0';

        end if;
      end if;
    end if;
  end process gen_proc;

  valid_o <= gen_valid;

end architecture arch;

casr/verif/casr30/casr30_test2/sim.vcd
$date
  Fri Feb 13 20:07:44 2026
$end
$version
  GHDL v0
$end
$timescale
  1 ps
$end
$scope module standard $end
$upscope $end
$scope module std_logic_1164 $end
$upscope $end
$scope module numeric_std $end
$upscope $end
$scope module casr_30 $end
$var reg 1 ! clk $end
$var reg 1 " rst $end
$var reg 1 # clr $end
$var reg 1 $ enb $end
$var reg 64 % seed_i[63:0] $end
$var reg 1 & init_i $end
$var reg 1 ' gen_i $end
$var reg 1 ( valid_o $end
$var reg 64 ) state_o[63:0] $end
$var reg 1 * clr_r $end
$var reg 1 + enb_r $end
$var reg 1 , gen_r $end
$var reg 66 - ext_casr_r[65:0] $end
$var reg 1 . seed_valid_r $end
$var reg 1 / gen_valid $end
$var reg 1 0 gen_valid_r $end
$var reg 1 1 o_bit $end
$scope module gen_out_lsb_0 $end
$upscope $end
$scope module gen_parallel_mode $end
$upscope $end
$upscope $end
$enddefinitions $end
#0
1!
0"
0#
0$
b0000000000000000000000000000000000000000000000000000000000000000 %
0&
0'
0(
b0000000000000000000000000000000000000000000000000000000000000000 )
0*
0+
0,
b000000000000000000000000000000000000000000000000000000000000000000 -
0.
0/
00
01
#5000
0!
#10000
1!
1"
1#
1$
#15000
0!
#20000
1!
0#
1*
1+
#25000
0!
#30000
1!
b0011011010111101000011110111010110100100101010111110000001111101 %
1&
1'
0*
#35000
0!
#40000
1!
0&
b0011011010111101000011110111010110100100101010111110000001111101 )
1,
b100110110101111010000111101110101101001001010101111100000011111010 -
1.
11
#45000
0!
#50000
1!
1(
b1101001010000101100100010001010010111111101010000011000010000101 )
b111010010100001011001000100010100101111111010100000110000100001011 -
1/
10
#55000
0!
#60000
1!
b0101111011001100111110111011011110000000101011000101100111001100 )
b001011110110011001111101110110111100000001010110001011001110011000 -
01
#65000
0!
#70000
1!
b1100001001110111000010001001000011000001101001101100111001110110 )
b011000010011101110000100010010000110000011010011011001110011101101 -
#75000
0!
#80000
1!
b0110011110010001100111011111100101100010101110100111001110010010 )
b001100111100100011001110111111001011000101011101001110011100100100 -
#85000
0!
#90000
1!
b1011100011111010111001000000111100110110100010111001110011111111 )
b110111000111110101110010000001111001101101000101110011100111111111 -
11
#95000
0!
#100000
1!
b1000110100001010001111100001000111010010110110001110011100000000 )
b010001101000010100011111000010001110100101101100011100111000000001 -
01
#105000
0!
#110000
1!
b1101010110011011010000110011101001011110010011010011100110000001 )
b111010101100110110100001100111010010111100100110100111001100000011 -
11
#115000
0!
#120000
1!
b0101010011101001011001011100101111000011111101011100111011000010 )
b001010100111010010110010111001011110000111111010111001110110000100 -
01
#125000
0!
#130000
1!
b1101011100101111001111000111100001100100000101000111001001100111 )
b111010111001011110011110001111000011001000001010001110010011001111 -
11
#135000
0!
#140000
1!
b0101000111100001110001101000110010111110001101101001111110111000 )
b001010001111000011100011010001100101111100011011010011111101110000 -
01
#145000
0!
#150000
1!
b1101101000110010011010101101011110000011010100101110000010001100 )
b011011010001100100110101011010111100000110101001011100000100011001 -
#155000
0!
#160000
1!
b0100101101011111101010100101000011000101010111100011000111010111 )
b101001011010111111010101001010000110001010101111000110001110101110 -
11
#165000
0!
#170000
1!
b0111100101000000101010111101100101101101010000110101101001010001 )
b101111001010000001010101111011001011011010100001101011010010100010 -
#175000
0!
#180000
1!
b0000111101100001101010000100111100100101011001010100101111011011 )
b100001111011000011010100001001111001001010110010101001011110110110 -
#185000
0!
#190000
1!
b1001000100110010101011001111000111111101001111010111100001001001 )
b110010001001100101010110011110001111111010011110101111000010010011 -
#195000
0!
#200000
1!
b1111101111011110101001110001101000000101110001010000110011111110 )
b011111011110111101010011100011010000001011100010100001100111111101 -
01
#205000
0!
#210000
1!
1#
b0000100001000010101110011010101100001100011011011001011100000010 )
b000001000010000101011100110101011000011000110110110010111000000100 -
#215000
0!
#220000
1!
b0001110011100110100011101010100110010110101001001111000110000111 )
1*
b100011100111001101000111010101001100101101010010011110001100001110 -
11
#225000
0!
#230000
1!
0#
0(
b1010011100111010110100101010111011110010101111110001101011001001 )
0,
b110100111001110101101001010101110111100101011111100011010110010011 -
0.
0/
00
#235000
0!
#240000
1!
b0001001000110100010101100111100010011010101111001101111011110000 %
1&
0*
#245000
0!
#250000
1!
0&
b0001001000110100010101100111100010011010101111001101111011110000 )
1,
b000010010001101000101011001111000100110101011110011011110111100000 -
1.
01
#255000
0!
#260000
1!
1(
b0011111101010110110100111000110111101010100001110100001000011000 )
b000111111010101101101001110001101111010101000011101000010000110000 -
1/
10
#265000
0!
#270000
1!
b0100000101010010010111001101010000101010110010010110011100101100 )
b001000001010100100101110011010100001010101100100101100111001011000 -
#275000
0!
#280000
1!
b1110001101011111110001110101011001101010011111110011100111100110 )
b011100011010111111100011101010110011010100111111100111001111001101 -
#285000
0!
#290000
1!
b0011010101000000011010010101001110101011100000011100111000111010 )
b000110101010000000110100101010011101010111000000111001110001110100 -
#295000
0!
#300000
1!
b0101010101100000101011110101110010101000110000100111001101001011 )
b101010101011000001010111101011100101010001100001001110011010010110 -
11
#305000
0!
#310000
1!
b0101010100110001101000010100011110101101011001111001110101111001 )
b101010101001100011010000101000111101011010110011110011101011110010 -
#315000
0!
#320000
1!
b0101010111011010101100110110100010100101001110001110010100001111 )
b101010101110110101011001101101000101001010011100011100101000011110 -
#325000
0!
#330000
1!
b0101010001001010100111010010110110111101110011010011110110010001 )
b101010100010010101001110100101101101111011100110100111101100100010 -
#335000
0!
#340000
1!
b0101011011111010111001011110010010000100011101011100010011111011 )
b101010110111110101110010111100100100001000111010111000100111110110 -
#345000
0!
#350000
1!
b0101001000001010001111000011111111001110100101000110111100001001 )
b101010010000010100011110000111111110011101001010001101111000010010 -
#355000
0!
#360000
1!
b0101111100011011010001100100000001110010111101101010000110011111 )
b101011111000110110100011001000000011100101111011010100001100111110 -
#365000
0!
#370000
1!
b0100000110101001011010111110000010011110000100101011001011100001 )
b101000001101010010110101111100000100111100001001010110010111000010 -
#375000
0!
#380000
1!
b0110001010101111001010000011000111100011001111101001111000110011 )
b101100010101011110010100000110001111000110011111010011110001100110 -
#385000
0!
#390000
1!
b0011011010100001111011000101101000110101110000101110001101011101 )
b100110110101000011110110001011010001101011100001011100011010111010 -
#395000
0!
#400000
1!
b1101001010110010001001101100101101010100011001100011010101000101 )
b111010010101100100010011011001011010101000110011000110101010001011 -
#405000
0!
#410000
1!
0'
b0101111010011111011110100111100101010110101110110101010101101100 )
b001011110100111110111101001111001010101101011101101010101011011000 -
01
#415000
0!
#420000
1!
1#
b1100001011100001000010111000111101010010100010010101010100100110 )
0,
b011000010111000010000101110001111010100101000100101010101001001101 -
#425000
0!
#430000
1!
0(
1*
0/
00
#435000
0!
#440000
1!
0#
0.
#445000
0!
#450000
1!
b1111111011011100101110101001100001110110010101000011001000010000 %
1&
0*
#455000
0!
#460000
1!
0&
b1111111011011100101110101001100001110110010101000011001000010000 )
b011111110110111001011101010011000011101100101010000110010000100001 -
1.
#465000
0!
#470000
1!
1'
#475000
0!
#480000
1!
1,
#485000
0!
#490000
1!
1(
b0000001001000111100010101110110010010011110101100101111100111001 )
b100000010010001111000101011101100100100111101011001011111001110010 -
1/
10
11
#495000
0!
#500000
1!
b1000011111101000110110100010011111111100010100111100000111001111 )
b110000111111010001101101000100111111111000101001111000001110011111 -
#505000
0!
#510000
1!
b1100100000101101010010110111100000000110110111000110001001110000 )
b011001000001011010100101101111000000001101101110001100010011100001 -
01
#515000
0!
#520000
1!
b0111110001100101011110010000110000001010010001101011011110011001 )
b101111100011001010111100100001100000010100100011010110111100110010 -
11
#525000
0!
#530000
1!
b0000011010111101000011111001011000011011111010101001000011101111 )
b100000110101111010000111110010110000110111110101010010000111011110 -
#535000
0!
#540000
1!
b1000101010000101100100001111001100101000001010101111100100100001 )
b110001010100001011001000011110011001010000010101011111001001000011 -
#545000
0!
#550000
1!
b1101101011001100111110010001110111101100011010100000111111110010 )
b011011010110011001111100100011101111011000110101000001111111100101 -
01
#555000
0!
#560000
1!
b0100101001110111000011111010010000100110101010110001000000011110 )
b001001010011101110000111110100100001001101010101100010000000111100 -
#565000
0!
#570000
1!
b1111101110010001100100001011111001111010101010011011100000100011 )
b111111011100100011001000010111110011110101010100110111000001000111 -
11
#575000
0!
#580000
1!
b0000100011111010111110011000001110001010101011101000110001110100 )
b000001000111110101111100110000011100010101010111010001100011101000 -
01
#585000
0!
#590000
1!
b0001110100001010000011101100010011011010101000101101011010010110 )
b000011101000010100000111011000100110110101010001011010110100101100 -
#595000
0!
#600000
1!
b0010010110011011000100100110111101001010101101100101001011110011 )
b100100101100110110001001001101111010010101011011001010010111100110 -
11
#605000
0!
#610000
1!
b1111110011101001101111111010000101111010100100111101111000011101 )
b111111100111010011011111110100001011110101001001111011110000111011 -
#615000
0!
#620000
1!
b0000011100101110100000001011001100001010111111000100001100100100 )
b000000111001011101000000010110011000010101111110001000011001001000 -
01
#625000
0!
#630000
1!
b0000100111100010110000011001110110011010000001101110010111111110 )
b000001001111000101100000110011101100110100000011011100101111111100 -
#635000
0!
#640000
1!
b0001111000110110011000101110010011101011000010100011110000000011 )
b100011110001101100110001011100100111010110000101000111100000000110 -
11
#645000
0!
#650000
1!
1#
b1010001101010011101101100011111100101001100110110100011000000101 )
b110100011010100111011011000111111001010011001101101000110000001011 -
#655000
0!
#660000
1!
b1011010101011100100100110100000111101110111010010110101100001100 )
1*
b010110101010111001001001101000001111011101110100101101011000011001 -
01
#665000
0!
#670000
1!
0#
0(
b1001010101000111111111010110001000100010001011110010100110010111 )
0,
b110010101010001111111110101100010001000100010111100101001100101111 -
0.
0/
00
11
#675000
0!
#680000
1!
b1010010110100101101001011010010110100101101001011010010110100101 %
1&
0*
#685000
0!
#690000
1!
0&
b1010010110100101101001011010010110100101101001011010010110100101 )
1,
b110100101101001011010010110100101101001011010010110100101101001011 -
1.
#695000
0!
#700000
1!
1(
b1011110010111100101111001011110010111100101111001011110010111100 )
b010111100101111001011110010111100101111001011110010111100101111001 -
1/
10
01
#705000
0!
#710000
1!
b1000011110000111100001111000011110000111100001111000011110000111 )
b110000111100001111000011110000111100001111000011110000111100001111 -
11
#715000
0!
#720000
1!
b1100100011001000110010001100100011001000110010001100100011001000 )
b011001000110010001100100011001000110010001100100011001000110010001 -
01
#725000
0!
#730000
1!
b0111110101111101011111010111110101111101011111010111110101111101 )
b101111101011111010111110101111101011111010111110101111101011111010 -
11
#735000
0!
#740000
1!
b0000010100000101000001010000010100000101000001010000010100000101 )
b100000101000001010000010100000101000001010000010100000101000001010 -
#745000
0!
#750000
1!
b1000110110001101100011011000110110001101100011011000110110001101 )
b110001101100011011000110110001101100011011000110110001101100011011 -
#755000
0!
#760000
1!
b1101010011010100110101001101010011010100110101001101010011010100 )
b011010100110101001101010011010100110101001101010011010100110101001 -
01
#765000
0!
#770000
1!
b0101011101010111010101110101011101010111010101110101011101010111 )
b101010111010101110101011101010111010101110101011101010111010101110 -
11
#775000
0!
#780000
1!
b0101000101010001010100010101000101010001010100010101000101010001 )
b101010001010100010101000101010001010100010101000101010001010100010 -
#785000
0!
#790000
1!
b0101101101011011010110110101101101011011010110110101101101011011 )
b101011011010110110101101101011011010110110101101101011011010110110 -
#795000
0!
#800000
1!
b0100100101001001010010010100100101001001010010010100100101001001 )
b101001001010010010100100101001001010010010100100101001001010010010 -
#805000
0!
#810000
1!
b0111111101111111011111110111111101111111011111110111111101111111 )
b101111111011111110111111101111111011111110111111101111111011111110 -
#815000
0!
#820000
1!
b0000000100000001000000010000000100000001000000010000000100000001 )
b100000001000000010000000100000001000000010000000100000001000000010 -
#825000
0!
#830000
1!
b1000001110000011100000111000001110000011100000111000001110000011 )
b110000011100000111000001110000011100000111000001110000011100000111 -
#835000
0!
#840000
1!
b1100010011000100110001001100010011000100110001001100010011000100 )
b011000100110001001100010011000100110001001100010011000100110001001 -
01
#845000
0!
#850000
1!
0'
b0110111101101111011011110110111101101111011011110110111101101111 )
b101101111011011110110111101101111011011110110111101101111011011110 -
11
#855000
0!
#860000
1!
1#
b0010000100100001001000010010000100100001001000010010000100100001 )
0,
b100100001001000010010000100100001001000010010000100100001001000010 -
#865000
0!
#870000
1!
0(
1*
0/
00
#875000
0!
#880000
1!
0#
0.
#885000
0!
#890000
1!
b0101101001011010010110100101101001011010010110100101101001011010 %
1&
0*
#895000
0!
#900000
1!
0&
b0101101001011010010110100101101001011010010110100101101001011010 )
b001011010010110100101101001011010010110100101101001011010010110100 -
1.
01
#905000
0!
#910000
1!
1'
#915000
0!
#920000
1!
1,
#925000
0!
#930000
1!
1(
b1100101111001011110010111100101111001011110010111100101111001011 )
b111001011110010111100101111001011110010111100101111001011110010111 -
1/
10
11
#935000
0!
#940000
1!
b0111100001111000011110000111100001111000011110000111100001111000 )
b001111000011110000111100001111000011110000111100001111000011110000 -
01
#945000
0!
#950000
1!
b1000110010001100100011001000110010001100100011001000110010001100 )
b010001100100011001000110010001100100011001000110010001100100011001 -
#955000
0!
#960000
1!
b1101011111010111110101111101011111010111110101111101011111010111 )
b111010111110101111101011111010111110101111101011111010111110101111 -
11
#965000
0!
#970000
1!
b0101000001010000010100000101000001010000010100000101000001010000 )
b001010000010100000101000001010000010100000101000001010000010100000 -
01
#975000
0!
#980000
1!
b1101100011011000110110001101100011011000110110001101100011011000 )
b011011000110110001101100011011000110110001101100011011000110110001 -
#985000
0!
#990000
1!
b0100110101001101010011010100110101001101010011010100110101001101 )
b101001101010011010100110101001101010011010100110101001101010011010 -
11
#995000
0!
#1000000
1!
b0111010101110101011101010111010101110101011101010111010101110101 )
b101110101011101010111010101110101011101010111010101110101011101010 -
#1005000
0!
#1010000
1!
b0001010100010101000101010001010100010101000101010001010100010101 )
b100010101000101010001010100010101000101010001010100010101000101010 -
#1015000
0!
#1020000
1!
b1011010110110101101101011011010110110101101101011011010110110101 )
b110110101101101011011010110110101101101011011010110110101101101011 -
#1025000
0!
#1030000
1!
b1001010010010100100101001001010010010100100101001001010010010100 )
b010010100100101001001010010010100100101001001010010010100100101001 -
01
#1035000
0!
#1040000
1!
b1111011111110111111101111111011111110111111101111111011111110111 )
b111110111111101111111011111110111111101111111011111110111111101111 -
11
#1045000
0!
#1050000
1!
b0001000000010000000100000001000000010000000100000001000000010000 )
b000010000000100000001000000010000000100000001000000010000000100000 -
01
#1055000
0!
#1060000
1!
b0011100000111000001110000011100000111000001110000011100000111000 )
b000111000001110000011100000111000001110000011100000111000001110000 -
#1065000
0!
#1070000
1!
b0100110001001100010011000100110001001100010011000100110001001100 )
b001001100010011000100110001001100010011000100110001001100010011000 -
#1075000
0!
#1080000
1!
b1111011011110110111101101111011011110110111101101111011011110110 )
b011110110111101101111011011110110111101101111011011110110111101101 -
#1085000
0!
#1090000
1!
1#
b0001001000010010000100100001001000010010000100100001001000010010 )
b000010010000100100001001000010010000100100001001000010010000100100 -
#1095000
0!
#1100000
1!
b0011111100111111001111110011111100111111001111110011111100111111 )
1*
b100111111001111110011111100111111001111110011111100111111001111110 -
11
#1105000
0!
#1110000
1!
0#
0(
b1100000111000001110000011100000111000001110000011100000111000001 )
0,
b111000001110000011100000111000001110000011100000111000001110000011 -
0.
0/
00
#1115000
0!
#1120000
1!
0*
#1125000
0!
#1130000
1!
b0000111100001111000011110000111100001111000011110000111100001111 %
1&
1,
#1135000
0!
#1140000
1!
0&
b0000111100001111000011110000111100001111000011110000111100001111 )
b100001111000011110000111100001111000011110000111100001111000011110 -
1.
#1145000
0!
#1150000
1!
1(
b1001000110010001100100011001000110010001100100011001000110010001 )
b110010001100100011001000110010001100100011001000110010001100100011 -
1/
10
#1155000
0!
#1160000
1!
b1111101011111010111110101111101011111010111110101111101011111010 )
b011111010111110101111101011111010111110101111101011111010111110101 -
01
#1165000
0!
#1170000
1!
b0000101000001010000010100000101000001010000010100000101000001010 )
b000001010000010100000101000001010000010100000101000001010000010100 -
#1175000
0!
#1180000
1!
b0001101100011011000110110001101100011011000110110001101100011011 )
b100011011000110110001101100011011000110110001101100011011000110110 -
11
#1185000
0!
#1190000
1!
b1010100110101001101010011010100110101001101010011010100110101001 )
b110101001101010011010100110101001101010011010100110101001101010011 -
#1195000
0!
#1200000
1!
b1010111010101110101011101010111010101110101011101010111010101110 )
b010101110101011101010111010101110101011101010111010101110101011101 -
01
#1205000
0!
#1210000
1!
b1010001010100010101000101010001010100010101000101010001010100010 )
b010100010101000101010001010100010101000101010001010100010101000101 -
#1215000
0!
#1220000
1!
b1011011010110110101101101011011010110110101101101011011010110110 )
b010110110101101101011011010110110101101101011011010110110101101101 -
#1225000
0!
#1230000
1!
b1001001010010010100100101001001010010010100100101001001010010010 )
b010010010100100101001001010010010100100101001001010010010100100101 -
#1235000
0!
#1240000
1!
b1111111011111110111111101111111011111110111111101111111011111110 )
b011111110111111101111111011111110111111101111111011111110111111101 -
#1245000
0!
#1250000
1!
b0000001000000010000000100000001000000010000000100000001000000010 )
b000000010000000100000001000000010000000100000001000000010000000100 -
#1255000
0!
#1260000
1!
b0000011100000111000001110000011100000111000001110000011100000111 )
b100000111000001110000011100000111000001110000011100000111000001110 -
11
#1265000
0!
#1270000
1!
b1000100110001001100010011000100110001001100010011000100110001001 )
b110001001100010011000100110001001100010011000100110001001100010011 -
#1275000
0!
#1280000
1!
b1101111011011110110111101101111011011110110111101101111011011110 )
b011011110110111101101111011011110110111101101111011011110110111101 -
01
#1285000
0!
#1290000
1!
b0100001001000010010000100100001001000010010000100100001001000010 )
b001000010010000100100001001000010010000100100001001000010010000100 -
#1295000
0!
#1300000
1!
b1110011111100111111001111110011111100111111001111110011111100111 )
b111100111111001111110011111100111111001111110011111100111111001111 -
11
#1305000
0!
#1310000
1!
b0011100000111000001110000011100000111000001110000011100000111000 )
b000111000001110000011100000111000001110000011100000111000001110000 -
01
#1315000
0!
#1320000
1!
b0100110001001100010011000100110001001100010011000100110001001100 )
b001001100010011000100110001001100010011000100110001001100010011000 -
#1325000
0!
#1330000
1!
b1111011011110110111101101111011011110110111101101111011011110110 )
b011110110111101101111011011110110111101101111011011110110111101101 -
#1335000
0!
#1340000
1!
b0001001000010010000100100001001000010010000100100001001000010010 )
b000010010000100100001001000010010000100100001001000010010000100100 -
#1345000
0!
#1350000
1!
b0011111100111111001111110011111100111111001111110011111100111111 )
b100111111001111110011111100111111001111110011111100111111001111110 -
11
#1355000
0!
#1360000
1!
b1100000111000001110000011100000111000001110000011100000111000001 )
b111000001110000011100000111000001110000011100000111000001110000011 -
#1365000
0!
#1370000
1!
b0110001001100010011000100110001001100010011000100110001001100010 )
b001100010011000100110001001100010011000100110001001100010011000100 -
01
#1375000
0!
#1380000
1!
b1011011110110111101101111011011110110111101101111011011110110111 )
b110110111101101111011011110110111101101111011011110110111101101111 -
11
#1385000
0!
#1390000
1!
b1001000010010000100100001001000010010000100100001001000010010000 )
b010010000100100001001000010010000100100001001000010010000100100001 -
01
#1395000
0!
#1400000
1!
0'
b1111100111111001111110011111100111111001111110011111100111111001 )
b111111001111110011111100111111001111110011111100111111001111110011 -
11
#1405000
0!
#1410000
1!
b0000111000001110000011100000111000001110000011100000111000001110 )
0,
b000001110000011100000111000001110000011100000111000001110000011100 -
01
#1415000
0!
#1420000
1!
0(
0/
00
