casr/casr_30.vhd
--------------------------------------------------------------------------------
-- Title       : Cellular Automata Shift Register (CASR) (Rule 30) 
-- Project     : hdl_rand
--------------------------------------------------------------------------------
-- File        : casr_30.vhd
-- Author      : Ameer Shalabi <ameershalabi94@gmail.com>
-- Created     : Fri Jan  9 14:22:18 2026
-- Last update : Tue Feb 10 15:15:17 2026
-- Platform    : -
-- Standard    : VHDL-2008
--------------------------------------------------------------------------------
-- Description: A Cellular Automata Shift Register (CASR) applying basic
-- rule 30. Has three output modes: 
-- 1) State LSB output (serial LSB)
-- 2) State MSB output (serial MSB)
-- 3) Full state output (parallel)
--------------------------------------------------------------------------------
library ieee;
use ieee.std_logic_1164.all;
use ieee.numeric_std.all;

entity casr_30 is
  generic (
    w_casr_g : integer := 8;
    -- control which bit to output
    -- '0' : output LSB bit
    -- '1' : output MSB bit
    o_bit_g : std_logic := '0';
    -- mode
    -- '0' : output is serial mode
    -- '1' : output is parallel
    o_mode_g : std_logic := '0'
  );
  port (
    -- ctrl ports
    clk : in std_logic; -- clock pin
    rst : in std_logic; -- active low rest pin
    clr : in std_logic; -- clear pin
    enb : in std_logic; -- enable pin

    seed_i : in std_logic_vector(w_casr_g-1 downto 0);
    init_i : in std_logic;
    gen_i  : in std_logic;

    valid_o : out std_logic;
    state_o : out std_logic_vector(w_casr_g-1 downto 0)

  );

end entity casr_30;

architecture arch of casr_30 is

  signal clr_r : std_logic;
  signal enb_r : std_logic;
  signal gen_r : std_logic;

  -- extended casr for generating the next state
  -- two additional bits are used to connect the 
  -- register ends
  signal ext_casr_r   : std_logic_vector(w_casr_g+1 downto 0);
  signal seed_valid_r : std_logic;

  -- output bit signals
  signal gen_valid   : std_logic;
  signal gen_valid_r : std_logic;
  signal o_bit       : std_logic;

begin

  -- Generate output bit and oputput modes
  -- When o_mode_g = '0' 
  -- Output is serial:
  -- i.e. a single bit is outputed at the LSB of the 
  -- state_o port. All other state_o bits are '0'
  -- -- if o_bit_g = '0', serial LSB mode :
  -- -- -- output bit is LSB of CASR state
  -- -- if o_bit_g = '1', serial MSB mode :
  -- -- -- output bit is MSB of CASR state

  -- connect output bit to LSB of next state
  gen_out_lsb_0 : if (o_bit_g = '0') generate
    o_bit <= ext_casr_r(w_casr_g+1);
  end generate gen_out_lsb_0;

  -- connect output bit to MSB of next state
  gen_out_lsb_1 : if (o_bit_g = '1') generate
    o_bit <= ext_casr_r(0);
  end generate gen_out_lsb_1;

  -- gen serial mode
  gen_serial_mode : if (o_mode_g = '0') generate

    serial_output_proc : process (o_bit)
    begin
      state_o    <= (others => '0');
      state_o(0) <= o_bit;
    end process serial_output_proc;

  end generate gen_serial_mode;

  -- When o_mode_g = '1'
  -- Full state output (parallel mode)
  -- i.e. all of the CASR state is put to the state_o
  -- in this mode, o_bit_g is not effective

  gen_parallel_mode : if (o_mode_g = '1') generate
    state_o <= ext_casr_r(w_casr_g downto 1);
  end generate gen_parallel_mode;


  ctrl_proc : process (clk, rst)
  begin
    if (rst = '0') then
      clr_r <= '0';
      enb_r <= '0';
    elsif rising_edge(clk) then
      clr_r <= clr;
      enb_r <= enb;
    end if;
  end process ctrl_proc;

  -- the extended casr is divided into two bit groups
  -- state bits (s), extention bits (e) as follows
  -- MSBext    
  -- |<-------|
  -- ||-state-|
  -- esss...ssse
  --  |------->|
  --           LSBext

  -- output bit is valid when
  gen_valid <= '1' when gen_valid_r = '1' else '0'; --and gen_r = '1' else '0';

  gen_proc : process (clk, rst)
    variable l              : std_logic;
    variable c              : std_logic;
    variable r              : std_logic;
    variable exp1           : std_logic;
    variable exp2           : std_logic;
    variable exp3           : std_logic;
    variable new_ext_casr_v : std_logic_vector(w_casr_g+1 downto 0);

  begin
    if (rst = '0') then
      gen_r        <= '0';
      gen_valid_r  <= '0';
      seed_valid_r <= '0';
      ext_casr_r   <= (others => '0');
    elsif rising_edge(clk) then
      if (enb_r = '1') then
        gen_r <= gen_i;
        -- output is invalid by default
        gen_valid_r <= '0';

        -- load the seed when init_i is high
        if (init_i = '1') then
          ext_casr_r(w_casr_g downto 1) <= seed_i;
          -- connect LSBext to the MSB of state
          ext_casr_r(0) <= seed_i(w_casr_g-1);
          -- connect MSBext to the LSB of state
          ext_casr_r(w_casr_g+1) <= seed_i(0);
          -- first output after init is invalid as
          -- it is the o_bit of the seed
          gen_valid_r  <= '0';
          seed_valid_r <= '1';

        -- if gen_i is high and init_i is low,
        -- generate the next state by applying the 
        -- expression on the left bit, state bit, and
        -- right bit
        elsif (gen_r = '1' and seed_valid_r = '1') then
          -- if generate is high, the first output is not yet
          -- valid, so valid is delayed a single clock cycle
          gen_valid_r <= '1';
          generate_next_state : for b in 1 to w_casr_g loop
            -- get left bit of state bit b
            l := ext_casr_r(b-1);
            -- get state bit b
            c := ext_casr_r(b);
            -- get right bit of state bit b
            r := ext_casr_r(b+1);
            -- apply expression l & not c & not r
            exp1 := l and not c and not r;
            -- apply expression not l & c
            exp2 := not l and c;
            -- apply expression not l & not c & r
            exp3 := not l and not c and r;

            -- store the new state bit
            new_ext_casr_v(b) := exp1 or exp2 or exp3;
            -- generate the extention bits for next round
            new_ext_casr_v(0)          := new_ext_casr_v(w_casr_g);
            new_ext_casr_v(w_casr_g+1) := new_ext_casr_v(1);
          end loop generate_next_state;
          ext_casr_r <= new_ext_casr_v;
        end if;
        if (clr_r = '1') then
          gen_r        <= '0';
          gen_valid_r  <= '0';
          seed_valid_r <= '0';

        end if;
      end if;
    end if;
  end process gen_proc;

  valid_o <= gen_valid;

end architecture arch;

casr/verif/casr30/casr30_test1/sim.vcd
$date
  Fri Feb 13 21:19:17 2026
$end
$version
  GHDL v0
$end
$timescale
  1 ps
$end
$scope module standard $end
$upscope $end
$scope module std_logic_1164 $end
$upscope $end
$scope module numeric_std $end
$upscope $end
$scope module casr_30 $end
$var reg 1 ! clk $end
$var reg 1 " rst $end
$var reg 1 # clr $end
$var reg 1 $ enb $end
$var reg 64 % seed_i[63:0] $end
$var reg 1 & init_i $end
$var reg 1 ' gen_i $end
$var reg 1 ( valid_o $end
$var reg 64 ) state_o[63:0] $end
$var reg 1 * clr_r $end
$var reg 1 + enb_r $end
$var reg 1 , gen_r $end
$var reg 66 - ext_casr_r[65:0] $end
$var reg 1 . seed_valid_r $end
$var reg 1 / gen_valid $end
$var reg 1 0 gen_valid_r $end
$var reg 1 1 o_bit $end
$scope module gen_out_lsb_0 $end
$upscope $end
$scope module gen_parallel_mode $end
$upscope $end
$upscope $end
$enddefinitions $end
#0
1!
0"
0#
0$
b0000000000000000000000000000000000000000000000000000000000000000 %
0&
0'
0(
b0000000000000000000000000000000000000000000000000000000000000000 )
0*
0+
0,
b000000000000000000000000000000000000000000000000000000000000000000 -
0.
0/
00
01
#5000
0!
#10000
1!
1"
1#
1$
#15000
0!
#20000
1!
0#
1*
1+
#25000
0!
#30000
1!
b0011011010111101000011110111010110100100101010111110000001111101 %
1&
1'
0*
#35000
0!
#40000
1!
0&
b0011011010111101000011110111010110100100101010111110000001111101 )
1,
b100110110101111010000111101110101101001001010101111100000011111010 -
1.
11
#45000
0!
#50000
1!
1(
b1101001010000101100100010001010010111111101010000011000010000101 )
b111010010100001011001000100010100101111111010100000110000100001011 -
1/
10
#55000
0!
#60000
1!
b0101111011001100111110111011011110000000101011000101100111001100 )
b001011110110011001111101110110111100000001010110001011001110011000 -
01
#65000
0!
#70000
1!
b1100001001110111000010001001000011000001101001101100111001110110 )
b011000010011101110000100010010000110000011010011011001110011101101 -
#75000
0!
#80000
1!
b0110011110010001100111011111100101100010101110100111001110010010 )
b001100111100100011001110111111001011000101011101001110011100100100 -
#85000
0!
#90000
1!
b1011100011111010111001000000111100110110100010111001110011111111 )
b110111000111110101110010000001111001101101000101110011100111111111 -
11
#95000
0!
#100000
1!
b1000110100001010001111100001000111010010110110001110011100000000 )
b010001101000010100011111000010001110100101101100011100111000000001 -
01
#105000
0!
#110000
1!
b1101010110011011010000110011101001011110010011010011100110000001 )
b111010101100110110100001100111010010111100100110100111001100000011 -
11
#115000
0!
#120000
1!
b0101010011101001011001011100101111000011111101011100111011000010 )
b001010100111010010110010111001011110000111111010111001110110000100 -
01
#125000
0!
#130000
1!
b1101011100101111001111000111100001100100000101000111001001100111 )
b111010111001011110011110001111000011001000001010001110010011001111 -
11
#135000
0!
#140000
1!
b0101000111100001110001101000110010111110001101101001111110111000 )
b001010001111000011100011010001100101111100011011010011111101110000 -
01
#145000
0!
#150000
1!
b1101101000110010011010101101011110000011010100101110000010001100 )
b011011010001100100110101011010111100000110101001011100000100011001 -
#155000
0!
#160000
1!
b0100101101011111101010100101000011000101010111100011000111010111 )
b101001011010111111010101001010000110001010101111000110001110101110 -
11
#165000
0!
#170000
1!
b0111100101000000101010111101100101101101010000110101101001010001 )
b101111001010000001010101111011001011011010100001101011010010100010 -
#175000
0!
#180000
1!
b0000111101100001101010000100111100100101011001010100101111011011 )
b100001111011000011010100001001111001001010110010101001011110110110 -
#185000
0!
#190000
1!
b1001000100110010101011001111000111111101001111010111100001001001 )
b110010001001100101010110011110001111111010011110101111000010010011 -
#195000
0!
#200000
1!
b1111101111011110101001110001101000000101110001010000110011111110 )
b011111011110111101010011100011010000001011100010100001100111111101 -
01
#205000
0!
#210000
1!
b0000100001000010101110011010101100001100011011011001011100000010 )
b000001000010000101011100110101011000011000110110110010111000000100 -
#215000
0!
#220000
1!
b0001110011100110100011101010100110010110101001001111000110000111 )
b100011100111001101000111010101001100101101010010011110001100001110 -
11
#225000
0!
#230000
1!
b1010011100111010110100101010111011110010101111110001101011001001 )
b110100111001110101101001010101110111100101011111100011010110010011 -
#235000
0!
#240000
1!
b1011100111001010010111101010001000011110100000011010101001111110 )
b010111001110010100101111010100010000111101000000110101010011111101 -
01
#245000
0!
#250000
1!
b1000111001111011110000101011011100100010110000101010101110000010 )
b010001110011110111100001010110111001000101100001010101011100000101 -
#255000
0!
#260000
1!
b1101001110001000011001101001000111110110011001101010100011000110 )
b011010011100010000110011010010001111101100110011010101000110001101 -
#265000
0!
#270000
1!
b0101110011011100101110101111101000010011101110101010110101101010 )
b001011100110111001011101011111010000100111011101010101101011010100 -
#275000
0!
#280000
1!
b1100011101000111100010100000101100111100100010101010010100101011 )
b111000111010001111000101000001011001111001000101010100101001010111 -
11
#285000
0!
#290000
1!
b0110100101101000110110110001100111000111110110101011110111101000 )
b001101001011010001101101100011001110001111101101010111101111010000 -
01
#295000
0!
#300000
1!
b1010111100101101010010011010111001101000010010101000010000101100 )
b010101111001011010100100110101110011010000100101010000100001011001 -
#305000
0!
#310000
1!
b1010000111100101011111101010001110101100111110101100111001100111 )
b110100001111001010111111010100011101011001111101011001110011001111 -
11
#315000
0!
#320000
1!
b1011001000111101000000101011010010100111000010100111001110111000 )
b010110010001111010000001010110100101001110000101001110011101110001 -
01
#325000
0!
#330000
1!
b1001111101000101100001101001011110111001100110111001110010001101 )
b110011111010001011000011010010111101110011001101110011100100011011 -
11
#335000
0!
#340000
1!
b1110000101101100110010101111000010001110111010001110011111010100 )
b011100001011011001100101011110000100011101110100011100111110101001 -
01
#345000
0!
#350000
1!
b0011001100100111011110100001100111010010001011010011100001010111 )
b100110011001001110111101000011001110100100010110100111000010101110 -
11
#355000
0!
#360000
1!
b1101110111111001000010110010111001011111011001011100110011010001 )
b111011101111110010000101100101110010111110110010111001100110100011 -
#365000
0!
#370000
1!
b0100010000001111100110011110001111000001001111000111011101011010 )
b001000100000011111001100111100011110000010011110001110111010110100 -
01
#375000
0!
#380000
1!
b1110111000010000111011100011010001100011110001101001000101001011 )
b111101110000100001110111000110100011000111100011010010001010010111 -
11
#385000
0!
#390000
1!
b0010001100111001001000110101011010110100011010101111101101111000 )
b000100011001110010010001101010110101101000110101011111011011110000 -
01
#395000
0!
#400000
1!
b0111010111001111111101010101001010010110101010100000100100001100 )
b001110101110011111111010101010010100101101010101000001001000011000 -
#405000
0!
#410000
1!
b1001010001110000000101010101111011110010101010110001111110010110 )
b010010100011100000001010101011110111100101010101100011111100101101 -
#415000
0!
#420000
1!
b1111011010011000001101010100001000011110101010011010000011110010 )
b011110110100110000011010101000010000111101010100110100000111100101 -
#425000
0!
#430000
1!
b0001001011101100010101010110011100100010101011101011000100011110 )
b000010010111011000101010101100111001000101010111010110001000111100 -
#435000
0!
#440000
1!
b0011111000100110110101010011100111110110101000101001101110100011 )
b100111110001001101101010100111001111101101010001010011011101000110 -
11
#445000
0!
#450000
1!
b1100001101111010010101011100111000010010101101101110100010110101 )
b111000011011110100101010111001110000100101011011011101000101101011 -
#455000
0!
#460000
1!
b0110010100001011110101000111001100111110100100100010110110010100 )
b001100101000010111101010001110011001111101001001000101101100101000 -
01
#465000
0!
#470000
1!
b1011110110011000010101101001110111000010111111110110010011110110 )
b010111101100110000101011010011101110000101111111101100100111101101 -
#475000
0!
#480000
1!
b1000010011101100110100101110010001100110000000010011111100010010 )
b010000100111011001101001011100100011001100000000100111111000100101 -
#485000
0!
#490000
1!
b1100111100100111010111100011111010111011000000111100000110111110 )
b011001111001001110101111000111110101110110000001111000001101111101 -
#495000
0!
#500000
1!
b0111000111111001010000110100001010001001100001000110001010000010 )
b001110001111110010100001101000010100010011000010001100010100000100 -
#505000
0!
#510000
1!
b1001101000001111011001010110011011011110110011101011011011000111 )
b110011010000011110110010101100110110111101100111010110110110001111 -
11
#515000
0!
#520000
1!
b1110101100010001001111010011101001000010011100101001001001101000 )
b011101011000100010011110100111010010000100111001010010010011010001 -
01
#525000
0!
#530000
1!
b0010100110111011110001011100101111100111100111101111111110101101 )
b100101001101110111100010111001011111001111001111011111111101011010 -
11
#535000
0!
#540000
1!
b1110111010001000011011000111100000111000111000100000000010100101 )
b111101110100010000110110001111000001110001110001000000000101001011 -
#545000
0!
#550000
1!
b0010001011011100101001101000110001001101001101110000000110111100 )
b000100010110111001010011010001100010011010011011100000001101111000 -
01
#555000
0!
#560000
1!
b0111011001000111101110101101011011110101110100011000001010000110 )
b001110110010001111011101011010110111101011101000110000010100001100 -
#565000
0!
#570000
1!
b1001001111101000100010100101001000010100010110101100011011001011 )
b110010011111010001000101001010010000101000101101011000110110010111 -
11
#575000
0!
#580000
1!
b1111110000101101110110111101111100110110110010100110101001111000 )
b011111100001011011101101111011111001101101100101001101010011110001 -
01
#585000
0!
#590000
1!
b0000011001100100010010000100000111010010011110111010101110001101 )
b100000110011001000100100001000001110100100111101110101011100011010 -
11
#595000
0!
#600000
1!
b1000101110111110111111001110001001011111100010001010100011010101 )
b110001011101111101111110011100010010111111000100010101000110101011 -
#605000
0!
#610000
1!
b1101100010000010000001110011011111000000110111011010110101010100 )
b011011000100000100000011100110111110000001101110110101101010101001 -
01
#615000
0!
#620000
1!
b0100110111000111000010011101000001100001010001001010010101010111 )
b101001101110001110000100111010000011000010100010010100101010101110 -
11
#625000
0!
#630000
1!
b0111010001101001100111100101100010110011011011111011110101010001 )
b101110100011010011001111001011000101100110110111110111101010100010 -
#635000
0!
#640000
1!
b0001011010101110111000111100110110011101001000001000010101011011 )
b100010110101011101110001111001101100111010010000010000101010110110 -
#645000
0!
#650000
1!
b1011001010100010001101000111010011100101111100011100110101001001 )
b110110010101000100011010001110100111001011111000111001101010010011 -
#655000
0!
#660000
1!
b1001111010110111010101101001011100111100000110100111010101111110 )
b010011110101101110101011010010111001111000001101001110101011111101 -
01
#665000
0!
#670000
1!
b1110001010010001010100101111000111000110001010111001010100000010 )
b011100010100100010101001011110001110001100010101110010101000000101 -
#675000
0!
#680000
1!
b0011011011111011010111100001101001101011011010001111010110000110 )
b000110110111110110101111000011010011010110110100011110101100001100 -
#685000
0!
#690000
1!
b0101001000001001010000110010101110101001001011010001010011001011 )
b101010010000010010100001100101011101010010010110100010100110010110 -
11
#695000
0!
#700000
1!
b0101111100011111011001011110100010101111111001011011011101111001 )
b101011111000111110110010111101000101011111110010110110111011110010 -
#705000
0!
#710000
1!
b0100000110100001001111000010110110100000001111001001000100001111 )
b101000001101000010011110000101101101000000011110010010001000011110 -
#715000
0!
#720000
1!
b0110001010110011110001100110010010110000010001111111101110010001 )
b101100010101100111100011001100100101100000100011111111011100100010 -
#725000
0!
#730000
1!
b0011011010011100011010111011111110011000111010000000100011111011 )
b100110110100111000110101110111111100110001110100000001000111110110 -
#735000
0!
#740000
1!
b1101001011100110101010001000000011101101001011000001110100001001 )
b111010010111001101010100010000000111011010010110000011101000010011 -
#745000
0!
#750000
1!
b0101111000111010101011011100000100100101111001100010010110011110 )
b001011110001110101010110111000001001001011110011000100101100111100 -
01
#755000
0!
#760000
1!
b1100001101001010101001000110001111111100001110110111110011100011 )
b111000011010010101010010001100011111111000011101101111100111000111 -
11
#765000
0!
#770000
1!
b0110010101111010101111101011010000000110010010010000011100110100 )
b001100101011110101011111010110100000001100100100100000111001101000 -
01
#775000
0!
#780000
1!
b1011110100001010100000101001011000001011111111111000100111010110 )
b010111101000010101000001010010110000010111111111110001001110101101 -
#785000
0!
#790000
1!
b1000010110011010110001101111001100011000000000001101111001010010 )
b010000101100110101100011011110011000110000000000011011110010100101 -
#795000
0!
#800000
1!
b1100110011101010011010100001110110101100000000010100001111011110 )
b011001100111010100110101000011101101011000000000101000011110111101 -
#805000
0!
#810000
1!
b0111011100101011101010110010010010100110000000110110010001000010 )
b001110111001010111010101100100100101001100000001101100100010000100 -
#815000
0!
#820000
1!
b1001000111101000101010011111111110111011000001010011111011100111 )
b110010001111010001010100111111111101110110000010100111110111001111 -
11
#825000
0!
#830000
1!
b1111101000101101101011100000000010001001100011011100001000111000 )
b011111010001011011010111000000000100010011000110111000010001110001 -
01
#835000
0!
#840000
1!
b0000101101100100101000110000000111011110110101000110011101001101 )
b100001011011001001010001100000001110111101101010001100111010011010 -
11
#845000
0!
#850000
1!
b1001100100111111101101011000001001000010010101101011100101110101 )
b110011001001111111011010110000010010000100101011010111001011101011 -
#855000
0!
#860000
1!
b1110111111000000100101001100011111100111110100101000111100010100 )
b011101111110000001001010011000111111001111101001010001111000101001 -
01
#865000
0!
#870000
1!
b0010000001100001111101110110100000111000010111101101000110110111 )
b100100000011000011111011101101000001110000101111011010001101101110 -
11
#875000
0!
#880000
1!
b1111000010110010000100010010110001001100110000100101101010010001 )
b111110000101100100001000100101100010011001100001001011010100100011 -
#885000
0!
#890000
1!
b0001100110011111001110111110011011110111011001111100101011111010 )
b000011001100111110011101111100110111101110110011111001010111110100 -
01
#895000
0!
#900000
1!
b0010111011100001110010000011101000010001001110000111101000001011 )
b100101110111000011100100000111010000100010011100001111010000010110 -
11
#905000
0!
#910000
1!
b1110001000110010011111000100101100111011110011001000101100011001 )
b111100010001100100111110001001011001110111100110010001011000110011 -
#915000
0!
#920000
1!
b0011011101011111100001101111100111001000011101111101100110101110 )
b000110111010111111000011011111001110010000111011111011001101011100 -
01
#925000
0!
#930000
1!
b0101000101000000110010100000111001111100100100000100111010100011 )
b101010001010000001100101000001110011111001001000001001110101000110 -
11
#935000
0!
#940000
1!
b0101101101100001011110110001001110000111111110001111001010110101 )
b101011011011000010111101100010011100001111111100011110010101101010 -
#945000
0!
#950000
1!
b0100100100110011000010011011110011001000000011010001111010010101 )
b101001001001100110000100110111100110010000000110100011110100101010 -
#955000
0!
#960000
1!
b0111111111011101100111101000011101111100000101011010001011110101 )
b101111111110111011001111010000111011111000001010110100010111101010 -
#965000
0!
#970000
1!
b0000000001000100111000101100100100000110001101001011011000010101 )
b100000000010001001110001011001001000001100011010010110110000101010 -
#975000
0!
#980000
1!
b1000000011101111001101100111111110001011010101111001001100110101 )
b110000000111011110011011001111111100010110101011110010011001101011 -
#985000
0!
#990000
1!
b1100000100100001110100111000000011011001010100001111110111010100 )
b011000001001000011101001110000000110110010101000011111101110101001 -
01
#995000
0!
#1000000
1!
b0110001111110010010111001100000101001111010110010000010001010111 )
b101100011111100100101110011000001010011110101100100000100010101110 -
11
#1005000
0!
#1010000
1!
b0011010000011111110001110110001101110001010011111000111011010001 )
b100110100000111111100011101100011011100010100111110001110110100010 -
#1015000
0!
#1020000
1!
b1101011000100000011010010011010100011011011100001101001001011011 )
b111010110001000000110100100110101000110110111000011010010010110111 -
#1025000
0!
#1030000
1!
0'
b0101001101110000101011111101010110101001000110010101111111001000 )
b001010011011100001010111111010101101010010001100101011111110010000 -
01
#1035000
0!
#1040000
1!
b1101110100011001101000000101010010101111101011110100000001111100 )
0,
b011011101000110011010000001010100101011111010111101000000011111001 -
#1045000
0!
#1050000
1!
0(
0/
00
