casr/casr_150.vhd
--------------------------------------------------------------------------------
-- Title       : Cellular Automata Shift Register (CASR) (Rule 150) 
-- Project     : hdl_rand
--------------------------------------------------------------------------------
-- File        : casr_150.vhd
-- Author      : Ameer Shalabi <ameershalabi94@gmail.com>
-- Created     : Sat Jan 10 21:46:02 2026
-- Last update : Sun Jan 11 11:35:25 2026
-- Platform    : -
-- Standard    : VHDL-2008
--------------------------------------------------------------------------------
-- Description: A Cellular Automata Shift Register (CASR) applying basic
-- rule 150. Has three output modes: 
-- 1) State LSB output (serial LSB)
-- 2) State MSB output (serial MSB)
-- 3) Full state output (parallel)
--------------------------------------------------------------------------------
library ieee;
use ieee.std_logic_1164.all;
use ieee.numeric_std.all;

entity casr_150 is
  generic (
    w_casr_g : integer := 8;
    -- control which bit to output
    -- '0' : output LSB bit
    -- '1' : output MSB bit
    o_bit_g : std_logic := '0';
    -- mode
    -- '0' : output is serial mode
    -- '1' : output is parallel
    o_mode_g : std_logic := '0'
  );
  port (
    -- ctrl ports
    clk : in std_logic; -- clock pin
    rst : in std_logic; -- active low rest pin
    clr : in std_logic; -- clear pin
    enb : in std_logic; -- enable pin

    seed_i : in std_logic_vector(w_casr_g-1 downto 0);
    init_i : in std_logic;
    gen_i  : in std_logic;

    valid_o : out std_logic;
    state_o : out std_logic_vector(w_casr_g-1 downto 0)

  );

end entity casr_150;

architecture arch of casr_150 is

  signal clr_r  : std_logic;
  signal enb_r  : std_logic;
  signal gen_r  : std_logic;

  -- extended casr for generating the next state
  -- two additional bits are used to connect the 
  -- register ends
  signal ext_casr_r : std_logic_vector(w_casr_g+1 downto 0);

  -- output bit signals
  signal gen_valid   : std_logic;
  signal gen_valid_r : std_logic;
  signal o_bit       : std_logic;

begin

  -- Generate output bit and oputput modes
  -- When o_mode_g = '0' 
  -- Output is serial:
  -- i.e. a single bit is outputed at the LSB of the 
  -- state_o port. All other state_o bits are '0'
  -- -- if o_bit_g = '0', serial LSB mode :
  -- -- -- output bit is LSB of CASR state
  -- -- if o_bit_g = '1', serial MSB mode :
  -- -- -- output bit is MSB of CASR state

  -- connect output bit to LSB of next state
  gen_out_lsb_0 : if (o_bit_g = '0') generate
    o_bit <= ext_casr_r(w_casr_g+1);
  end generate gen_out_lsb_0;

  -- connect output bit to MSB of next state
  gen_out_lsb_1 : if (o_bit_g = '1') generate
    o_bit <= ext_casr_r(0);
  end generate gen_out_lsb_1;

  -- gen serial mode
  gen_serial_mode : if (o_mode_g = '0') generate

    serial_output_proc : process (o_bit)
    begin
      state_o    <= (others => '0');
      state_o(0) <= o_bit;
    end process serial_output_proc;

  end generate gen_serial_mode;

  -- When o_mode_g = '1'
  -- Full state output (parallel mode)
  -- i.e. all of the CASR state is put to the state_o
  -- in this mode, o_bit_g is not effective

  gen_parallel_mode : if (o_mode_g = '1') generate
    state_o <= ext_casr_r(w_casr_g downto 1);
  end generate gen_parallel_mode;


  ctrl_proc : process (clk, rst)
  begin
    if (rst = '0') then
      clr_r <= '0';
      enb_r <= '0';
    elsif rising_edge(clk) then
      clr_r <= clr;
      enb_r <= enb;
    end if;
  end process ctrl_proc;

  -- the extended casr is divided into two bit groups
  -- state bits (s), extention bits (e) as follows
  -- MSBext    
  -- |<-------|
  -- ||-state-|
  -- esss...ssse
  --  |------->|
  --           LSBext

  -- output bit is valid when
  gen_valid <= '1' when gen_valid_r = '1' and gen_r = '1' else '0';

  gen_proc : process (clk, rst)
    variable l              : std_logic;
    variable c              : std_logic;
    variable r              : std_logic;
    variable exp1           : std_logic;
    variable new_ext_casr_v : std_logic_vector(w_casr_g+1 downto 0);

  begin
    if (rst = '0') then
      gen_r       <= '0';
      gen_valid_r <= '0';
      ext_casr_r  <= (others => '0');
    elsif rising_edge(clk) then
      if (enb_r = '1') then
        gen_r       <= gen_i;
        -- output is invalid by default
        gen_valid_r <= '0';

        -- load the seed when init_i is high
        if (init_i = '1') then
          ext_casr_r(w_casr_g downto 1) <= seed_i;
          -- connect LSBext to the MSB of state
          ext_casr_r(0) <= seed_i(w_casr_g-1);
          -- connect MSBext to the LSB of state
          ext_casr_r(w_casr_g+1) <= seed_i(0);
          -- first output after init is invalid as
          -- it is the o_bit of the seed
          gen_valid_r <= '0';

        else
          -- if gen_i is high and init_i is low,
          -- generate the next state by applying the 
          -- expression on the left bit, state bit, and
          -- right bit
          if (gen_r = '1') then
            -- if generate is high, the first output is not yet
            -- valid, so valid is delayed a single clock cycle
            gen_valid_r <= '1';
            generate_next_state : for b in 1 to w_casr_g loop
              -- get left bit of state bit b
              l := ext_casr_r(b-1);
              -- get state bit b
              c := ext_casr_r(b);
              -- get right bit of state bit b
              r := ext_casr_r(b+1);
              --exp1 := l xor r;
              exp1 := l xor c xor r;
              -- store the new state bit
              new_ext_casr_v(b) := exp1;
              -- generate the extention bits for next round
              new_ext_casr_v(0)          := new_ext_casr_v(w_casr_g);
              new_ext_casr_v(w_casr_g+1) := new_ext_casr_v(1);
            end loop generate_next_state;
            ext_casr_r <= new_ext_casr_v;
          end if;
        end if;
        if (clr_r = '1') then
          gen_r       <= '0';
          gen_valid_r <= '0';
        end if;
      end if;
    end if;
  end process gen_proc;

  valid_o <= gen_valid;

end architecture arch;

casr/verif/casr150/sim.vcd
$date
  Wed Feb  4 01:22:59 2026
$end
$version
  GHDL v0
$end
$timescale
  1 ps
$end
$scope module standard $end
$upscope $end
$scope module std_logic_1164 $end
$upscope $end
$scope module numeric_std $end
$upscope $end
$scope module casr_150 $end
$var reg 1 ! clk $end
$var reg 1 " rst $end
$var reg 1 # clr $end
$var reg 1 $ enb $end
$var reg 256 % seed_i[255:0] $end
$var reg 1 & init_i $end
$var reg 1 ' gen_i $end
$var reg 1 ( valid_o $end
$var reg 256 ) state_o[255:0] $end
$var reg 1 * clr_r $end
$var reg 1 + enb_r $end
$var reg 1 , gen_r $end
$var reg 258 - ext_casr_r[257:0] $end
$var reg 1 . gen_valid $end
$var reg 1 / gen_valid_r $end
$var reg 1 0 o_bit $end
$scope module gen_out_lsb_0 $end
$upscope $end
$scope module gen_parallel_mode $end
$upscope $end
$upscope $end
$enddefinitions $end
#0
1!
0"
0#
0$
b0000000000000000000000000000000000000000000000000000000000000000000000000000000000000000000000000000000000000000000000000000000000000000000000000000000000000000000000000000000000000000000000000000000000000000000000000000000000000000000000000000000000000000 %
0&
0'
0(
b0000000000000000000000000000000000000000000000000000000000000000000000000000000000000000000000000000000000000000000000000000000000000000000000000000000000000000000000000000000000000000000000000000000000000000000000000000000000000000000000000000000000000000 )
0*
0+
0,
b000000000000000000000000000000000000000000000000000000000000000000000000000000000000000000000000000000000000000000000000000000000000000000000000000000000000000000000000000000000000000000000000000000000000000000000000000000000000000000000000000000000000000000 -
0.
0/
00
#5000
0!
#10000
1!
1"
1#
1$
#15000
0!
#20000
1!
0#
b1111110001111111111111011101010111100111010011101111010011000010010011110111111100010111001000101110111101110101100010101100010011011011001100111111101001011110001111000100110110001010001011000011011010111101000011110111010110100100101010111110000001111101 %
1&
1'
1*
1+
#25000
0!
#30000
1!
0&
b1111110001111111111111011101010111100111010011101111010011000010010011110111111100010111001000101110111101110101100010101100010011011011001100111111101001011110001111000100110110001010001011000011011010111101000011110111010110100100101010111110000001111101 )
0*
b111111100011111111111110111010101111001110100111011110100110000100100111101111111000101110010001011101111011101011000101011000100110110110011001111111010010111100011110001001101100010100010110000110110101111010000111101110101101001001010101111100000011111011 -
10
#35000
0!
#40000
1!
1,
#45000
0!
#50000
1!
1(
b1111101010111111111110001001010011011010011101000110011100100111111101100011111010110010111101100100011000100100010110100010111100000000110011011111001111001101010110101111000001011011011000100100000010011001100101100010010000111111101010011101000010111000 )
b011111010101111111111100010010100110110100111010001100111001001111111011000111110101100101111011001000110001001000101101000101111000000001100110111110011110011010101101011110000010110110110001001000000100110011001011000100100001111111010100111010000101110001 -
1.
1/
00
#55000
0!
#60000
1!
b0111001010011111111101011111011100000011101001101001101011111011111000010101110010001110011000011110100101111110110000110110011010000001001100001110110110110001010000100110100011000000000101111110000111100110011100010111111001011111001011101001100110010101 )
b101110010100111111111010111110111000000111010011010011010111110111110000101011100100011100110000111101001011111101100001101100110100000010011000011101101101100010100001001101000110000000001011111100001111001100111000101111110010111110010111010011001100101010 -
10
#65000
0!
#70000
1!
b0010111011101111111001001110001010000101001110001110001001110001110100110100101111010101100100101100111100111100001001000001100011000011110010010100000000001011011001111000110100100000001100111101001011011001101010110011110111001110111001001110011001110101 )
b100101110111011111110010011100010100001010011100011100010011100011101001101001011110101011001001011001111001111000010010000011000110000111100100101000000000010110110011110001101001000000011001111010010110110011010101100111101110011101110010011100110011101010 -
#75000
0!
#80000
1!
b1110010001000111110111110101011011001101110101010101011110101010100111000111100110010100011111100011011011011010011111100010010100100101101111110110000000011000000110110101000111110000010011011001111000000110001010001101100010110100010111110101100110100101 )
b111100100010001111101111101010110110011011101010101010111101010101001110001111001100101000111111000110110110110100111111000100101001001011011111101100000000110000001101101010001111100000100110110011110000001100010100011011000101101000101111101011001101001011 -
#85000
0!
#90000
1!
b1101111011101011100011100101000000110000100101010101001100101010111010101011011001110110101111010100000000000011101111010111110111111100000111100001000000100100001000000101101011101000111100000110110100001001011011010000010110000110110011100100011000111100 )
b011011110111010111000111001010000001100001001010101010011001010101110101010110110011101101011110101000000000000111011110101111101111111000001111000010000001001000010000001011010111010001111000001101101000010010110110100000101100001101100111001000110001111001 -
00
#95000
0!
#100000
1!
b0000110001001001010101011101100001001001111101010101110011101010010010101000000110100000100110010110000000000101000110010011100011111010001011010011100001111110011100001100001001001101011010001000000110011111000000011000110001001000001101011110100101011011 )
b100001100010010010101010111011000010010011111010101011100111010100100101010000001101000001001100101100000000001010001100100111000111110100010110100111000011111100111000011000010010011010110100010000001100111110000000110001100010010000011010111101001010110110 -
10
#105000
0!
#110000
1!
b1001001011111111010101001000010011111110111001010100101101001011111110101100001000110001111001110001000000001101101001111101010101110011011000011101010010111101101010010010011111110001000011011100001001101110100000100101001011111100010001001100111101000000 )
b010010010111111110101010010000100111111101110010101001011010010111111101011000010001100011110011100010000000011011010011111010101011100110110000111010100101111011010100100100111111100010000110111000010011011101000001001010010111111000100010011001111010000001 -
00
#115000
0!
#120000
1!
b1111111001111110010101111100111101111100010111010111100001111001111100100010011101001010110110101011100000010000001110111001010100101100000100101001011110011000001011111111101111101011100100001010011110000100110001111101111001111010111011110011011001100001 )
b111111110011111100101011111001111011111000101110101111000011110011111001000100111010010101101101010111000000100000011101110010101001011000001001010010111100110000010111111111011111010111001000010100111100001001100011111011110011110101110111100110110011000011 -
10
#125000
0!
#130000
1!
0'
b1111110110111101110100111011011000111010110010010011010010110110111011110111101001111010000000101001010000111000010100010111010111100010001111101111001101100100011001111111000111001001011110011011101101001111001010111000110110110010010001101100000110010010 )
b011111101101111011101001110110110001110101100100100110100101101101110111101111010011110100000001010010100001110000101000101110101111000100011111011110011011001000110011111110001110010010111100110111011010011110010101110001101101100100100011011000001100100101 -
00
