casr/casr_90.vhd
--------------------------------------------------------------------------------
-- Title       : Cellular Automata Shift Register (CASR) (Rule 90) 
-- Project     : hdl_rand
--------------------------------------------------------------------------------
-- File        : casr_90.vhd
-- Author      : Ameer Shalabi <ameershalabi94@gmail.com>
-- Created     : Sat Jan 10 17:49:02 2026
-- Last update : Sun Jan 11 11:35:30 2026
-- Platform    : -
-- Standard    : VHDL-2008
--------------------------------------------------------------------------------
-- Description: A Cellular Automata Shift Register (CASR) applying basic
-- rule 90. Has three output modes: 
-- 1) State LSB output (serial LSB)
-- 2) State MSB output (serial MSB)
-- 3) Full state output (parallel)
--------------------------------------------------------------------------------
library ieee;
use ieee.std_logic_1164.all;
use ieee.numeric_std.all;

entity casr_90 is
  generic (
    w_casr_g : integer := 8;
    -- control which bit to output
    -- '0' : output LSB bit
    -- '1' : output MSB bit
    o_bit_g : std_logic := '0';
    -- mode
    -- '0' : output is serial mode
    -- '1' : output is parallel
    o_mode_g : std_logic := '0'
  );
  port (
    -- ctrl ports
    clk : in std_logic; -- clock pin
    rst : in std_logic; -- active low rest pin
    clr : in std_logic; -- clear pin
    enb : in std_logic; -- enable pin

    seed_i : in std_logic_vector(w_casr_g-1 downto 0);
    init_i : in std_logic;
    gen_i  : in std_logic;

    valid_o : out std_logic;
    state_o : out std_logic_vector(w_casr_g-1 downto 0)

  );

end entity casr_90;

architecture arch of casr_90 is

  signal clr_r  : std_logic;
  signal enb_r  : std_logic;
  signal gen_r  : std_logic;

  -- extended casr for generating the next state
  -- two additional bits are used to connect the 
  -- register ends
  signal ext_casr_r : std_logic_vector(w_casr_g+1 downto 0);

  -- output bit signals
  signal gen_valid   : std_logic;
  signal gen_valid_r : std_logic;
  signal o_bit       : std_logic;

begin

  -- Generate output bit and oputput modes
  -- When o_mode_g = '0' 
  -- Output is serial:
  -- i.e. a single bit is outputed at the LSB of the 
  -- state_o port. All other state_o bits are '0'
  -- -- if o_bit_g = '0', serial LSB mode :
  -- -- -- output bit is LSB of CASR state
  -- -- if o_bit_g = '1', serial MSB mode :
  -- -- -- output bit is MSB of CASR state

  -- connect output bit to LSB of next state
  gen_out_lsb_0 : if (o_bit_g = '0') generate
    o_bit <= ext_casr_r(w_casr_g+1);
  end generate gen_out_lsb_0;

  -- connect output bit to MSB of next state
  gen_out_lsb_1 : if (o_bit_g = '1') generate
    o_bit <= ext_casr_r(0);
  end generate gen_out_lsb_1;

  -- gen serial mode
  gen_serial_mode : if (o_mode_g = '0') generate

    serial_output_proc : process (o_bit)
    begin
      state_o    <= (others => '0');
      state_o(0) <= o_bit;
    end process serial_output_proc;

  end generate gen_serial_mode;

  -- When o_mode_g = '1'
  -- Full state output (parallel mode)
  -- i.e. all of the CASR state is put to the state_o
  -- in this mode, o_bit_g is not effective

  gen_parallel_mode : if (o_mode_g = '1') generate
    state_o <= ext_casr_r(w_casr_g downto 1);
  end generate gen_parallel_mode;


  ctrl_proc : process (clk, rst)
  begin
    if (rst = '0') then
      clr_r <= '0';
      enb_r <= '0';
    elsif rising_edge(clk) then
      clr_r <= clr;
      enb_r <= enb;
    end if;
  end process ctrl_proc;

  -- the extended casr is divided into two bit groups
  -- state bits (s), extention bits (e) as follows
  -- MSBext    
  -- |<-------|
  -- ||-state-|
  -- esss...ssse
  --  |------->|
  --           LSBext

  -- output bit is valid when
  gen_valid <= '1' when gen_valid_r = '1' and gen_r = '1' else '0';

  gen_proc : process (clk, rst)
    variable l              : std_logic;
    variable r              : std_logic;
    variable exp1           : std_logic;
    variable new_ext_casr_v : std_logic_vector(w_casr_g+1 downto 0);

  begin
    if (rst = '0') then
      gen_r       <= '0';
      gen_valid_r <= '0';
      ext_casr_r  <= (others => '0');
    elsif rising_edge(clk) then
      if (enb_r = '1') then
        gen_r       <= gen_i;
        -- output is invalid by default
        gen_valid_r <= '0';

        -- load the seed when init_i is high
        if (init_i = '1') then
          ext_casr_r(w_casr_g downto 1) <= seed_i;
          -- connect LSBext to the MSB of state
          ext_casr_r(0) <= seed_i(w_casr_g-1);
          -- connect MSBext to the LSB of state
          ext_casr_r(w_casr_g+1) <= seed_i(0);
          -- first output after init is invalid as
          -- it is the o_bit of the seed
          gen_valid_r <= '0';

        else
          -- if gen_i is high and init_i is low,
          -- generate the next state by applying the 
          -- expression on the left bit, state bit, and
          -- right bit
          if (gen_r = '1') then
            -- if generate is high, the first output is not yet
            -- valid, so valid is delayed a single clock cycle
            gen_valid_r <= '1';
            generate_next_state : for b in 1 to w_casr_g loop
              -- get left bit of state bit b
              l := ext_casr_r(b-1);
              -- get right bit of state bit b
              r := ext_casr_r(b+1);
              --exp1 := l xor r;
              exp1 := l xor r;
              -- store the new state bit
              new_ext_casr_v(b) := exp1;
              -- generate the extention bits for next round
              new_ext_casr_v(0)          := new_ext_casr_v(w_casr_g);
              new_ext_casr_v(w_casr_g+1) := new_ext_casr_v(1);
            end loop generate_next_state;
            ext_casr_r <= new_ext_casr_v;
          end if;
        end if;
        if (clr_r = '1') then
          gen_r       <= '0';
          gen_valid_r <= '0';
        end if;
      end if;
    end if;
  end process gen_proc;

  valid_o <= gen_valid;

end architecture arch;

casr/verif/casr90/sim.vcd
$date
  Wed Feb  4 00:44:12 2026
$end
$version
  GHDL v0
$end
$timescale
  1 ps
$end
$scope module standard $end
$upscope $end
$scope module std_logic_1164 $end
$upscope $end
$scope module numeric_std $end
$upscope $end
$scope module casr_90 $end
$var reg 1 ! clk $end
$var reg 1 " rst $end
$var reg 1 # clr $end
$var reg 1 $ enb $end
$var reg 128 % seed_i[127:0] $end
$var reg 1 & init_i $end
$var reg 1 ' gen_i $end
$var reg 1 ( valid_o $end
$var reg 128 ) state_o[127:0] $end
$var reg 1 * clr_r $end
$var reg 1 + enb_r $end
$var reg 1 , gen_r $end
$var reg 130 - ext_casr_r[129:0] $end
$var reg 1 . gen_valid $end
$var reg 1 / gen_valid_r $end
$var reg 1 0 o_bit $end
$scope module gen_out_lsb_0 $end
$upscope $end
$scope module gen_parallel_mode $end
$upscope $end
$upscope $end
$enddefinitions $end
#0
1!
0"
0#
0$
b00000000000000000000000000000000000000000000000000000000000000000000000000000000000000000000000000000000000000000000000000000000 %
0&
0'
0(
b00000000000000000000000000000000000000000000000000000000000000000000000000000000000000000000000000000000000000000000000000000000 )
0*
0+
0,
b0000000000000000000000000000000000000000000000000000000000000000000000000000000000000000000000000000000000000000000000000000000000 -
0.
0/
00
#5000
0!
#10000
1!
1"
1#
1$
#15000
0!
#20000
1!
0#
b11011011001100111111101001011110001111000100110110001010001011000011011010111101000011110111010110100100101010111110000001111101 %
1&
1'
1*
1+
#25000
0!
#30000
1!
0&
b11011011001100111111101001011110001111000100110110001010001011000011011010111101000011110111010110100100101010111110000001111101 )
0*
b1110110110011001111111010010111100011110001001101100010100010110000110110101111010000111101110101101001001010101111100000011111011 -
10
#35000
0!
#40000
1!
1,
#45000
0!
#50000
1!
1(
b01011011111111100000100110010011011001101011110111010001010011100111011000100100100110010101000110011011000000100011000011000101 )
b1010110111111111000001001100100110110011010111101110100010100111001110110001001001001100101010001100110110000001000110000110001010 -
1.
1/
#55000
0!
#60000
1!
b00011010000000110001011111101111011111100010010101001010001110111101011101011011011111100000101111111011100001010111100111101000 )
b0000110100000001100010111111011110111111000100101010010100011101111010111010110110111111000001011111110111000010101111001111010000 -
00
#65000
0!
#70000
1!
b00111001000001111010010000101001010000110101100000110001011010100100010100011011010000110001001000001010110010000100111100100100 )
b0001110010000011110100100001010010100001101011000001100010110101001000101000110110100001100010010000010101100100001001111001001000 -
#75000
0!
#80000
1!
b01101110100011001001101001000110001001110001110001111010011000011010100010111011001001111010110100010000111101001011100111011010 )
b0011011101000110010011010010001100010011100011100011110100110000110101000101110110010011110101101000100001111010010111001110110100 -
#85000
0!
#90000
1!
b11101010010111110111100110101111010111011011011011001001111100111000010100101011110111001000110010101001100100110010111101011001 )
b1111010100101111101111001101011110101110110110110110010011111001110000101001010111101110010001100101010011001001100101111010110011 -
10
#95000
0!
#100000
1!
b00100001100100010100111110001001000101011011011011110111000111101100100011000010010101110101111100000111111011111100100100011111 )
b1001000011001000101001111100010010001010110110110111101110001111011001000110000100101011101011111000001111110111111001001000111110 -
#105000
0!
#110000
1!
b11010011111010100011100011010110101000011011011010010101101100101111010111100101100001010001000110001100001010000111011010110001 )
b1110100111110101000111000110101101010000110110110100101011011001011110101111001011000010100010001100011000010100001110110101100011 -
#115000
0!
#120000
1!
b01001110001000010110110111000110000100111011011001100001101111001001000100111001110010001010101111011110010001001101011000111011 )
b1010011100010000101101101110001100001001110110110011000011011110010010001001110011100100010101011110111100100010011010110001110110 -
#125000
0!
#130000
1!
0'
b00111011010100100110110101101111001011101011011111110011101001110110101011101111011101010000001001010011101010111100011101101011 )
b1001110110101001001101101011011110010111010110111111100111010011101101010111011110111010100000010010100111010101111000111011010110 -
